[
  {
    "id": "456503",
    "name": "韓式醃白蘿蔔",
    "url": "https://icook.tw/recipes/456503",
    "preview_ingredients": "白蘿蔔、二砂糖、壽司醋、水",
    "ingredients": [
      "白蘿蔔1條",
      "二砂糖2/3杯",
      "壽司醋2/3杯",
      "水2/3杯"
    ],
    "structured_ingredients": [
      {
        "name": "白蘿蔔",
        "quantity": 1.0,
        "unit": "條"
      },
      {
        "name": "二砂糖",
        "quantity": 0.667,
        "unit": "杯"
      },
      {
        "name": "壽司醋",
        "quantity": 0.667,
        "unit": "杯"
      },
      {
        "name": "水",
        "quantity": 0.667,
        "unit": "杯"
      }
    ],
    "steps": [
      "白蘿蔔削皮，切丁、切條、切片都可以（喜歡吃辣可以放入辣椒丁）",
      "將糖、醋、水等比放入鍋中煮至沸騰",
      "用密封的玻璃器皿先將蘿蔔做分裝，再倒入煮沸的步驟二"
    ],
    "combined_text": "韓式醃白蘿蔔。食材：白蘿蔔1條，二砂糖2/3杯，壽司醋2/3杯，水2/3杯。做法：白蘿蔔削皮，切丁、切條、切片都可以（喜歡吃辣可以放入辣椒丁），將糖、醋、水等比放入鍋中煮至沸騰，用密封的玻璃器皿先將蘿蔔做分裝，再倒入煮沸的步驟二。",
    "image_path": "白蘿蔔/456503_韓式醃白蘿蔔.jpg"
  },
  {
    "id": "475367",
    "name": "白蘿蔔燒肉片",
    "url": "https://icook.tw/recipes/475367",
    "preview_ingredients": "白蘿蔔、豬五花肉片、鹽、蔥白、白胡椒粉、醬油、蔥綠、米酒、味醂、開水、二砂糖",
    "ingredients": [
      "白蘿蔔315克",
      "豬五花肉片330克",
      "蔥白適量",
      "蔥綠適量",
      "開水4大匙",
      "鹽½小匙",
      "白胡椒粉¼小匙",
      "米酒1小匙",
      "醬油2大匙",
      "味醂1大匙",
      "米酒1大匙",
      "二砂糖1大匙"
    ],
    "structured_ingredients": [
      {
        "name": "白蘿蔔",
        "quantity": 315.0,
        "unit": "克"
      },
      {
        "name": "豬五花肉片",
        "quantity": 330.0,
        "unit": "克"
      },
      {
        "name": "蔥白",
        "quantity": "適量",
        "unit": null
      },
      {
        "name": "蔥綠",
        "quantity": "適量",
        "unit": null
      },
      {
        "name": "開水",
        "quantity": 4.0,
        "unit": "大匙"
      },
      {
        "name": "鹽",
        "quantity": 0.5,
        "unit": "小匙"
      },
      {
        "name": "白胡椒粉",
        "quantity": 0.25,
        "unit": "小匙"
      },
      {
        "name": "米酒",
        "quantity": 1.0,
        "unit": "小匙"
      },
      {
        "name": "醬油",
        "quantity": 2.0,
        "unit": "大匙"
      },
      {
        "name": "味醂",
        "quantity": 1.0,
        "unit": "大匙"
      },
      {
        "name": "米酒",
        "quantity": 1.0,
        "unit": "大匙"
      },
      {
        "name": "二砂糖",
        "quantity": 1.0,
        "unit": "大匙"
      }
    ],
    "steps": [
      "白蘿蔔去皮，切成厚度約0.5公分的扇形，電鍋外鍋放蒸架並倒入半米杯水先蒸過（開關跳起即可，免燜）。\n五花肉片切適口大小，醃漬15分鐘。蔥白切圈、蔥綠切圈。",
      "小火，些許油，爆香蔥白。",
      "中火，肉片下鍋炒熟。",
      "放入白蘿蔔翻炒幾下。",
      "調味料下鍋和食材炒勻。",
      "開水下鍋拌勻。",
      "煮滾時，轉中小火燒煮至濃稠（大約10分鐘，期間偶爾）。",
      "撒下蔥綠拌一拌，完成。"
    ],
    "combined_text": "白蘿蔔燒肉片。食材：白蘿蔔315克，豬五花肉片330克，蔥白適量，蔥綠適量，開水4大匙，鹽½小匙，白胡椒粉¼小匙，米酒1小匙，醬油2大匙，味醂1大匙，米酒1大匙，二砂糖1大匙。做法：白蘿蔔去皮，切成厚度約0.5公分的扇形，電鍋外鍋放蒸架並倒入半米杯水先蒸過（開關跳起即可，免燜）。\n五花肉片切適口大小，醃漬15分鐘。蔥白切圈、蔥綠切圈。，小火，些許油，爆香蔥白。，中火，肉片下鍋炒熟。，放入白蘿蔔翻炒幾下。，調味料下鍋和食材炒勻。，開水下鍋拌勻。，煮滾時，轉中小火燒煮至濃稠（大約10分鐘，期間偶爾）。，撒下蔥綠拌一拌，完成。。",
    "image_path": "白蘿蔔/475367_白蘿蔔燒肉片.jpg"
  },
  {
    "id": "475639",
    "name": "素燒白蘿蔔湯",
    "url": "https://icook.tw/recipes/475639",
    "preview_ingredients": "白蘿蔔、乾香菇、八角、月桂葉、薑片、醬油、蠔油、鹽、鮮味炒手、蔥花、水",
    "ingredients": [
      "白蘿蔔200克",
      "乾香菇50g",
      "八角2顆",
      "月桂葉3片",
      "薑片5片",
      "醬油1大匙",
      "蠔油1大匙",
      "鹽2小匙",
      "鮮味炒手1小匙",
      "蔥花適量",
      "水1500cc"
    ],
    "structured_ingredients": [
      {
        "name": "白蘿蔔",
        "quantity": 200.0,
        "unit": "克"
      },
      {
        "name": "乾香菇",
        "quantity": 50.0,
        "unit": "g"
      },
      {
        "name": "八角",
        "quantity": 2.0,
        "unit": "顆"
      },
      {
        "name": "月桂葉",
        "quantity": 3.0,
        "unit": "片"
      },
      {
        "name": "薑片",
        "quantity": 5.0,
        "unit": "片"
      },
      {
        "name": "醬油",
        "quantity": 1.0,
        "unit": "大匙"
      },
      {
        "name": "蠔油",
        "quantity": 1.0,
        "unit": "大匙"
      },
      {
        "name": "鹽",
        "quantity": 2.0,
        "unit": "小匙"
      },
      {
        "name": "鮮味炒手",
        "quantity": 1.0,
        "unit": "小匙"
      },
      {
        "name": "蔥花",
        "quantity": "適量",
        "unit": null
      },
      {
        "name": "水",
        "quantity": 1500.0,
        "unit": "cc"
      }
    ],
    "steps": [
      "乾香菇泡熱水半小時左右",
      "白蘿蔔去皮切塊",
      "熱油鍋煎白蘿蔔去掉生味",
      "煎到2面微焦黃後盛起備用",
      "熱油鍋，放入薑片爆香",
      "放入月桂葉跟八角一起爆香",
      "放入泡軟的香菇，香菇水，白蘿蔔，醬油，蠔油，鹽，鮮味炒手一起煮沸",
      "煮沸後轉小火煮15分鐘即完成",
      "撒上蔥花，清甜好喝"
    ],
    "combined_text": "素燒白蘿蔔湯。食材：白蘿蔔200克，乾香菇50g，八角2顆，月桂葉3片，薑片5片，醬油1大匙，蠔油1大匙，鹽2小匙，鮮味炒手1小匙，蔥花適量，水1500cc。做法：乾香菇泡熱水半小時左右，白蘿蔔去皮切塊，熱油鍋煎白蘿蔔去掉生味，煎到2面微焦黃後盛起備用，熱油鍋，放入薑片爆香，放入月桂葉跟八角一起爆香，放入泡軟的香菇，香菇水，白蘿蔔，醬油，蠔油，鹽，鮮味炒手一起煮沸，煮沸後轉小火煮15分鐘即完成，撒上蔥花，清甜好喝。",
    "image_path": "白蘿蔔/475639_素燒白蘿蔔湯.jpg"
  },
  {
    "id": "470673",
    "name": "紅燒白蘿蔔",
    "url": "https://icook.tw/recipes/470673",
    "preview_ingredients": "絞肉豬、白蘿蔔、薑片、蔥白蔥綠、辣椒、蒜片、醬油、糖、水",
    "ingredients": [
      "絞肉豬150克",
      "白蘿蔔1",
      "薑片5片",
      "蔥白蔥綠1小匙",
      "辣椒1條",
      "蒜片4瓣",
      "醬油3大匙",
      "糖1大匙",
      "水適量"
    ],
    "structured_ingredients": [
      {
        "name": "絞肉豬",
        "quantity": 150.0,
        "unit": "克"
      },
      {
        "name": "白蘿蔔",
        "quantity": 1.0,
        "unit": null
      },
      {
        "name": "薑片",
        "quantity": 5.0,
        "unit": "片"
      },
      {
        "name": "蔥白蔥綠",
        "quantity": 1.0,
        "unit": "小匙"
      },
      {
        "name": "辣椒",
        "quantity": 1.0,
        "unit": "條"
      },
      {
        "name": "蒜片",
        "quantity": 4.0,
        "unit": "瓣"
      },
      {
        "name": "醬油",
        "quantity": 3.0,
        "unit": "大匙"
      },
      {
        "name": "糖",
        "quantity": 1.0,
        "unit": "大匙"
      },
      {
        "name": "水",
        "quantity": "適量",
        "unit": null
      }
    ],
    "steps": [
      "下油先將薑、蔥白、蒜頭炒出味道",
      "下絞肉 翻炒至出水",
      "炒至表面上色",
      "加入3大匙醬油、1大匙糖（或味醂）、1小杯水，稍微拌炒",
      "加入白蘿蔔及淹沒食材的水、少許胡椒鹽",
      "等水滾白蘿蔔煮爛\n這次使用的是金小萬速度還蠻快的，但要開蓋注意避免水煮乾\n之前是用瓦斯爐煮，蓋上鍋蓋小火煮個20分鐘，白蘿蔔切小塊，會熟透的比較快",
      "白蘿蔔有煮透後，稍微收醬汁，加入辣椒、蔥綠 稍微滾一下就可以上桌囉"
    ],
    "combined_text": "紅燒白蘿蔔。食材：絞肉豬150克，白蘿蔔1，薑片5片，蔥白蔥綠1小匙，辣椒1條，蒜片4瓣，醬油3大匙，糖1大匙，水適量。做法：下油先將薑、蔥白、蒜頭炒出味道，下絞肉 翻炒至出水，炒至表面上色，加入3大匙醬油、1大匙糖（或味醂）、1小杯水，稍微拌炒，加入白蘿蔔及淹沒食材的水、少許胡椒鹽，等水滾白蘿蔔煮爛\n這次使用的是金小萬速度還蠻快的，但要開蓋注意避免水煮乾\n之前是用瓦斯爐煮，蓋上鍋蓋小火煮個20分鐘，白蘿蔔切小塊，會熟透的比較快，白蘿蔔有煮透後，稍微收醬汁，加入辣椒、蔥綠 稍微滾一下就可以上桌囉。",
    "image_path": "白蘿蔔/470673_紅燒白蘿蔔.jpg"
  },
  {
    "id": "479476",
    "name": "電鍋出好菜—日式白蘿蔔佃煮",
    "url": "https://icook.tw/recipes/479476",
    "preview_ingredients": "白蘿蔔、海帶結、日式高湯包、油豆腐、醬油（3大匙）、日式油豆腐、二砂糖",
    "ingredients": [
      "白蘿蔔1條",
      "海帶結200克",
      "油豆腐6塊",
      "日式油豆腐適量",
      "日式高湯包1包",
      "醬油（3大匙）45cc",
      "二砂糖1大匙"
    ],
    "structured_ingredients": [
      {
        "name": "白蘿蔔",
        "quantity": 1.0,
        "unit": "條"
      },
      {
        "name": "海帶結",
        "quantity": 200.0,
        "unit": "克"
      },
      {
        "name": "油豆腐",
        "quantity": 6.0,
        "unit": "塊"
      },
      {
        "name": "日式油豆腐",
        "quantity": "適量",
        "unit": null
      },
      {
        "name": "日式高湯包",
        "quantity": 1.0,
        "unit": "包"
      },
      {
        "name": "醬油（3大匙）",
        "quantity": 45.0,
        "unit": "cc"
      },
      {
        "name": "二砂糖",
        "quantity": 1.0,
        "unit": "大匙"
      }
    ],
    "steps": [
      "食材隨喜❤️最重要的有白蘿蔔，\n想加水煮蛋、紅蘿蔔也是可以的。\n\n做法\n1）白蘿蔔洗淨削皮，切厚片、中心劃十字\n2）其餘食材洗淨備用\n3）起一鍋水，水開放入白蘿蔔片、一小匙太白粉煮20分鐘去除澀味後撈起備用\n4）所有食材放入內鍋\n5）加入調味料，加水沒過食材\n6）電鍋外鍋2杯水，開始烹煮",
      "7）完成✅可擺上蔥絲點綴"
    ],
    "combined_text": "電鍋出好菜—日式白蘿蔔佃煮。食材：白蘿蔔1條，海帶結200克，油豆腐6塊，日式油豆腐適量，日式高湯包1包，醬油（3大匙）45cc，二砂糖1大匙。做法：食材隨喜❤️最重要的有白蘿蔔，\n想加水煮蛋、紅蘿蔔也是可以的。\n\n做法\n1）白蘿蔔洗淨削皮，切厚片、中心劃十字\n2）其餘食材洗淨備用\n3）起一鍋水，水開放入白蘿蔔片、一小匙太白粉煮20分鐘去除澀味後撈起備用\n4）所有食材放入內鍋\n5）加入調味料，加水沒過食材\n6）電鍋外鍋2杯水，開始烹煮，7）完成✅可擺上蔥絲點綴。",
    "image_path": "白蘿蔔/479476_電鍋出好菜—日式白蘿蔔佃煮.jpg"
  },
  {
    "id": "477337",
    "name": "百香大根（百香果醃白蘿蔔）",
    "url": "https://icook.tw/recipes/477337",
    "preview_ingredients": "白蘿蔔、百香果、鹽、糖",
    "ingredients": [
      "白蘿蔔1根",
      "百香果2顆",
      "鹽1大匙",
      "糖1小匙"
    ],
    "structured_ingredients": [
      {
        "name": "白蘿蔔",
        "quantity": 1.0,
        "unit": "根"
      },
      {
        "name": "百香果",
        "quantity": 2.0,
        "unit": "顆"
      },
      {
        "name": "鹽",
        "quantity": 1.0,
        "unit": "大匙"
      },
      {
        "name": "糖",
        "quantity": 1.0,
        "unit": "小匙"
      }
    ],
    "steps": [
      "白蘿蔔去皮，切成好入口的片狀。",
      "切好的白蘿蔔灑上一大匙鹽拌勻，靜置約10-15分鐘。照片中是小半條白蘿蔔的份量。我自己覺得鹽的份量就是每片蘿蔔都有沾附到一層薄薄的鹽即可。",
      "百香果切開，取出果肉及果汁，倒在大碗或保鮮盒中備用。",
      "靜置完成，出水的白蘿蔔，倒掉有澀味的水後，再用力擠乾水份。然後用可飲用的水，再次將蘿蔔片淘洗一會兒，洗去多餘鹽份。照片中是整根白蘿蔔的量，這些水全部都是白蘿蔔排出的水。",
      "將百香果汁、白蘿蔔、糖於大碗或保鮮盒拌勻，若覺得百香果汁太少，可補些飲用水。",
      "冰箱放置一晚後即可取出食用。"
    ],
    "combined_text": "百香大根（百香果醃白蘿蔔）。食材：白蘿蔔1根，百香果2顆，鹽1大匙，糖1小匙。做法：白蘿蔔去皮，切成好入口的片狀。，切好的白蘿蔔灑上一大匙鹽拌勻，靜置約10-15分鐘。照片中是小半條白蘿蔔的份量。我自己覺得鹽的份量就是每片蘿蔔都有沾附到一層薄薄的鹽即可。，百香果切開，取出果肉及果汁，倒在大碗或保鮮盒中備用。，靜置完成，出水的白蘿蔔，倒掉有澀味的水後，再用力擠乾水份。然後用可飲用的水，再次將蘿蔔片淘洗一會兒，洗去多餘鹽份。照片中是整根白蘿蔔的量，這些水全部都是白蘿蔔排出的水。，將百香果汁、白蘿蔔、糖於大碗或保鮮盒拌勻，若覺得百香果汁太少，可補些飲用水。，冰箱放置一晚後即可取出食用。。",
    "image_path": "白蘿蔔/477337_百香大根（百香果醃白蘿蔔）.jpg"
  },
  {
    "id": "472057",
    "name": "酸甜醃白蘿蔔",
    "url": "https://icook.tw/recipes/472057",
    "preview_ingredients": "白蘿蔔、鹽巴、檸檬汁、糖、氣泡水",
    "ingredients": [
      "白蘿蔔1根",
      "鹽巴2大匙",
      "檸檬汁2大匙",
      "糖80克",
      "氣泡水1杯"
    ],
    "structured_ingredients": [
      {
        "name": "白蘿蔔",
        "quantity": 1.0,
        "unit": "根"
      },
      {
        "name": "鹽巴",
        "quantity": 2.0,
        "unit": "大匙"
      },
      {
        "name": "檸檬汁",
        "quantity": 2.0,
        "unit": "大匙"
      },
      {
        "name": "糖",
        "quantity": 80.0,
        "unit": "克"
      },
      {
        "name": "氣泡水",
        "quantity": 1.0,
        "unit": "杯"
      }
    ],
    "steps": [
      "蘿蔔切薄片、丁塊\n不同的形狀，口感吃起來也不一樣",
      "切好的蘿蔔灑上鹽巴\n\n重點：使蘿蔔出水，可以手捏看看蘿蔔有沒有軟\n\n變軟、出水後，清洗蘿蔔，避免過鹹",
      "調製酸甜液體檸檬汁+糖+氣泡水\n淹過蘿蔔，可以嚐看看酸甜的味道夠不夠",
      "放置冰箱，一個晚上，吃炸雞的時候可以配著吃"
    ],
    "combined_text": "酸甜醃白蘿蔔。食材：白蘿蔔1根，鹽巴2大匙，檸檬汁2大匙，糖80克，氣泡水1杯。做法：蘿蔔切薄片、丁塊\n不同的形狀，口感吃起來也不一樣，切好的蘿蔔灑上鹽巴\n\n重點：使蘿蔔出水，可以手捏看看蘿蔔有沒有軟\n\n變軟、出水後，清洗蘿蔔，避免過鹹，調製酸甜液體檸檬汁+糖+氣泡水\n淹過蘿蔔，可以嚐看看酸甜的味道夠不夠，放置冰箱，一個晚上，吃炸雞的時候可以配著吃。",
    "image_path": "白蘿蔔/472057_酸甜醃白蘿蔔.jpg"
  },
  {
    "id": "470871",
    "name": "白蘿蔔肉粥",
    "url": "https://icook.tw/recipes/470871",
    "preview_ingredients": "白蘿蔔、豬絞肉、胡椒鹽、蝦皮、醬油、白米、水、紅頭酥、香菜",
    "ingredients": [
      "白蘿蔔1/2根",
      "豬絞肉100克",
      "蝦皮適量",
      "白米1.5杯",
      "水15杯",
      "紅頭酥適量",
      "香菜適量",
      "胡椒鹽適量",
      "醬油1-2匙"
    ],
    "structured_ingredients": [
      {
        "name": "白蘿蔔",
        "quantity": 0.5,
        "unit": "根"
      },
      {
        "name": "豬絞肉",
        "quantity": 100.0,
        "unit": "克"
      },
      {
        "name": "蝦皮",
        "quantity": "適量",
        "unit": null
      },
      {
        "name": "白米",
        "quantity": 1.5,
        "unit": "杯"
      },
      {
        "name": "水",
        "quantity": 15.0,
        "unit": "杯"
      },
      {
        "name": "紅頭酥",
        "quantity": "適量",
        "unit": null
      },
      {
        "name": "香菜",
        "quantity": "適量",
        "unit": null
      },
      {
        "name": "胡椒鹽",
        "quantity": "適量",
        "unit": null
      },
      {
        "name": "醬油1-",
        "quantity": 2.0,
        "unit": "匙"
      }
    ],
    "steps": [
      "白蘿蔔去皮，切小塊；白米洗淨，瀝水",
      "起油鍋，放入豬絞肉炒至變白，加入蝦皮、紅頭酥爆香，加入白米、醬油拌炒一下，加入白蘿蔔、水煮沸後，轉小火，煮約15-20分鐘至白米開花，用胡椒鹽調味",
      "食用時，加入香菜即可"
    ],
    "combined_text": "白蘿蔔肉粥。食材：白蘿蔔1/2根，豬絞肉100克，蝦皮適量，白米1.5杯，水15杯，紅頭酥適量，香菜適量，胡椒鹽適量，醬油1-2匙。做法：白蘿蔔去皮，切小塊；白米洗淨，瀝水，起油鍋，放入豬絞肉炒至變白，加入蝦皮、紅頭酥爆香，加入白米、醬油拌炒一下，加入白蘿蔔、水煮沸後，轉小火，煮約15-20分鐘至白米開花，用胡椒鹽調味，食用時，加入香菜即可。",
    "image_path": "白蘿蔔/470871_白蘿蔔肉粥.jpg"
  },
  {
    "id": "460475",
    "name": "清燉牛肉洋蔥白蘿蔔",
    "url": "https://icook.tw/recipes/460475",
    "preview_ingredients": "牛嫩煎里脊、洋蔥、鹽、白蘿蔔、雞粉、滷包、米酒",
    "ingredients": [
      "牛嫩煎里脊800克",
      "洋蔥1顆",
      "白蘿蔔0.25條",
      "滷包1包",
      "米酒1大匙",
      "鹽1大匙",
      "雞粉2大匙"
    ],
    "structured_ingredients": [
      {
        "name": "牛嫩煎里脊",
        "quantity": 800.0,
        "unit": "克"
      },
      {
        "name": "洋蔥",
        "quantity": 1.0,
        "unit": "顆"
      },
      {
        "name": "白蘿蔔",
        "quantity": 0.25,
        "unit": "條"
      },
      {
        "name": "滷包",
        "quantity": 1.0,
        "unit": "包"
      },
      {
        "name": "米酒",
        "quantity": 1.0,
        "unit": "大匙"
      },
      {
        "name": "鹽",
        "quantity": 1.0,
        "unit": "大匙"
      },
      {
        "name": "雞粉",
        "quantity": 2.0,
        "unit": "大匙"
      }
    ],
    "steps": [
      "牛肉、洋蔥、白蘿蔔切塊備用",
      "熱鍋放入牛肉與洋蔥炒至焦化",
      "將煎鍋食材移至湯鍋加入1000 CC熱水、滷包、米酒煮滾10分鐘",
      "加入白蘿蔔塊小火煮40分鐘，加入鹽與雞粉調味即可"
    ],
    "combined_text": "清燉牛肉洋蔥白蘿蔔。食材：牛嫩煎里脊800克，洋蔥1顆，白蘿蔔0.25條，滷包1包，米酒1大匙，鹽1大匙，雞粉2大匙。做法：牛肉、洋蔥、白蘿蔔切塊備用，熱鍋放入牛肉與洋蔥炒至焦化，將煎鍋食材移至湯鍋加入1000 CC熱水、滷包、米酒煮滾10分鐘，加入白蘿蔔塊小火煮40分鐘，加入鹽與雞粉調味即可。",
    "image_path": "白蘿蔔/460475_清燉牛肉洋蔥白蘿蔔.jpg"
  },
  {
    "id": "473822",
    "name": "烤烏魚子佐蒜苗白蘿蔔",
    "url": "https://icook.tw/recipes/473822",
    "preview_ingredients": "烏魚子、白蘿蔔、蒜苗、高粱酒",
    "ingredients": [
      "烏魚子1片",
      "烏魚子1片",
      "白蘿蔔1段",
      "白蘿蔔1段",
      "蒜苗2支",
      "蒜苗2支",
      "高粱酒2杯",
      "高粱酒2杯"
    ],
    "structured_ingredients": [
      {
        "name": "烏魚子",
        "quantity": 1.0,
        "unit": "片"
      },
      {
        "name": "烏魚子",
        "quantity": 1.0,
        "unit": "片"
      },
      {
        "name": "白蘿蔔",
        "quantity": 1.0,
        "unit": "段"
      },
      {
        "name": "白蘿蔔",
        "quantity": 1.0,
        "unit": "段"
      },
      {
        "name": "蒜苗",
        "quantity": 2.0,
        "unit": "支"
      },
      {
        "name": "蒜苗",
        "quantity": 2.0,
        "unit": "支"
      },
      {
        "name": "高粱酒",
        "quantity": 2.0,
        "unit": "杯"
      },
      {
        "name": "高粱酒",
        "quantity": 2.0,
        "unit": "杯"
      }
    ],
    "steps": [
      "取淺盤，將烏魚子浸泡高粱酒",
      "將浸泡的酒倒掉，重新加入高粱酒，點火烤烏魚子",
      "烤至有香氣表皮微焦即可",
      "放涼後才斜切片，白蘿蔔也切薄片，蒜苗切片，組裝成盤"
    ],
    "combined_text": "烤烏魚子佐蒜苗白蘿蔔。食材：烏魚子1片，烏魚子1片，白蘿蔔1段，白蘿蔔1段，蒜苗2支，蒜苗2支，高粱酒2杯，高粱酒2杯。做法：取淺盤，將烏魚子浸泡高粱酒，將浸泡的酒倒掉，重新加入高粱酒，點火烤烏魚子，烤至有香氣表皮微焦即可，放涼後才斜切片，白蘿蔔也切薄片，蒜苗切片，組裝成盤。",
    "image_path": "白蘿蔔/473822_烤烏魚子佐蒜苗白蘿蔔.jpg"
  },
  {
    "id": "473326",
    "name": "清燉白蘿蔔牛肉湯/家常菜",
    "url": "https://icook.tw/recipes/473326",
    "preview_ingredients": "牛腩、白蘿蔔、鹽、雞骨架、米酒、洋蔥、薑、青蔥、八角",
    "ingredients": [
      "牛腩250克",
      "白蘿蔔200克",
      "雞骨架130克",
      "洋蔥30克",
      "鹽適量",
      "米酒2大匙",
      "薑3片",
      "青蔥1根",
      "八角1個"
    ],
    "structured_ingredients": [
      {
        "name": "牛腩",
        "quantity": 250.0,
        "unit": "克"
      },
      {
        "name": "白蘿蔔",
        "quantity": 200.0,
        "unit": "克"
      },
      {
        "name": "雞骨架",
        "quantity": 130.0,
        "unit": "克"
      },
      {
        "name": "洋蔥",
        "quantity": 30.0,
        "unit": "克"
      },
      {
        "name": "鹽",
        "quantity": "適量",
        "unit": null
      },
      {
        "name": "米酒",
        "quantity": 2.0,
        "unit": "大匙"
      },
      {
        "name": "薑",
        "quantity": 3.0,
        "unit": "片"
      },
      {
        "name": "青蔥",
        "quantity": 1.0,
        "unit": "根"
      },
      {
        "name": "八角",
        "quantity": 1.0,
        "unit": "個"
      }
    ],
    "steps": [
      "備料。牛腩切塊，白蘿蔔滾刀塊，洋蔥切絲。",
      "煮一鍋水，汆燙牛腩及雞骨架，去血水。",
      "另煮一鍋水，約1500CC，水滾放入薑片、蔥段、八角、牛腩、雞骨架、洋蔥、米酒。",
      "水滾後轉小火燉煮1小時，再放入鹽及白蘿蔔，續煮20分鐘。最後熄火燜10分鐘，是讓白蘿蔔入味且口感不會過爛的好方法。",
      "起鍋，加入少許蔥花及香菜。"
    ],
    "combined_text": "清燉白蘿蔔牛肉湯/家常菜。食材：牛腩250克，白蘿蔔200克，雞骨架130克，洋蔥30克，鹽適量，米酒2大匙，薑3片，青蔥1根，八角1個。做法：備料。牛腩切塊，白蘿蔔滾刀塊，洋蔥切絲。，煮一鍋水，汆燙牛腩及雞骨架，去血水。，另煮一鍋水，約1500CC，水滾放入薑片、蔥段、八角、牛腩、雞骨架、洋蔥、米酒。，水滾後轉小火燉煮1小時，再放入鹽及白蘿蔔，續煮20分鐘。最後熄火燜10分鐘，是讓白蘿蔔入味且口感不會過爛的好方法。，起鍋，加入少許蔥花及香菜。。",
    "image_path": "白蘿蔔/473326_清燉白蘿蔔牛肉湯_家常菜.jpg"
  },
  {
    "id": "463345",
    "name": "滷白蘿蔔",
    "url": "https://icook.tw/recipes/463345",
    "preview_ingredients": "白蘿蔔、醬油、水",
    "ingredients": [
      "白蘿蔔1條",
      "醬油適量",
      "水適量"
    ],
    "structured_ingredients": [
      {
        "name": "白蘿蔔",
        "quantity": 1.0,
        "unit": "條"
      },
      {
        "name": "醬油",
        "quantity": "適量",
        "unit": null
      },
      {
        "name": "水",
        "quantity": "適量",
        "unit": null
      }
    ],
    "steps": [
      "將皮洗乾淨，削皮時可以削多一點，切成1公分圓塊。",
      "將白蘿蔔放進鍋中，加入水(淹到蘿蔔)，開中小火，水滾後加入適量醬油，將蘿蔔煮熟就完成囉!"
    ],
    "combined_text": "滷白蘿蔔。食材：白蘿蔔1條，醬油適量，水適量。做法：將皮洗乾淨，削皮時可以削多一點，切成1公分圓塊。，將白蘿蔔放進鍋中，加入水(淹到蘿蔔)，開中小火，水滾後加入適量醬油，將蘿蔔煮熟就完成囉!。",
    "image_path": "白蘿蔔/463345_滷白蘿蔔.jpg"
  },
  {
    "id": "478918",
    "name": "菜頭排骨貢丸湯",
    "url": "https://icook.tw/recipes/478918",
    "preview_ingredients": "菜頭、排骨、貢丸、玉米",
    "ingredients": [
      "菜頭1根",
      "排骨5.6塊",
      "貢丸5.6顆",
      "玉米2.3根"
    ],
    "structured_ingredients": [
      {
        "name": "菜頭",
        "quantity": 1.0,
        "unit": "根"
      },
      {
        "name": "排骨",
        "quantity": 5.6,
        "unit": "塊"
      },
      {
        "name": "貢丸",
        "quantity": 5.6,
        "unit": "顆"
      },
      {
        "name": "玉米",
        "quantity": 2.3,
        "unit": "根"
      }
    ],
    "steps": [
      "先將菜頭削皮切塊",
      "排骨汆燙去血水",
      "將排骨與菜頭放入鍋中燉，水滾後轉小火約20-30分鐘，加貢丸玉米，菜頭軟了，我自己愛吃香菇加了一點",
      "加鹽調味，起鍋切香菜增添香味，也能加點白胡椒"
    ],
    "combined_text": "菜頭排骨貢丸湯。食材：菜頭1根，排骨5.6塊，貢丸5.6顆，玉米2.3根。做法：先將菜頭削皮切塊，排骨汆燙去血水，將排骨與菜頭放入鍋中燉，水滾後轉小火約20-30分鐘，加貢丸玉米，菜頭軟了，我自己愛吃香菇加了一點，加鹽調味，起鍋切香菜增添香味，也能加點白胡椒。",
    "image_path": "白蘿蔔/478918_菜頭排骨貢丸湯.jpg"
  },
  {
    "id": "471183",
    "name": "小菜_醃白蘿蔔（超簡單快速）",
    "url": "https://icook.tw/recipes/471183",
    "preview_ingredients": "白蘿蔔、水果醋、鹽",
    "ingredients": [
      "白蘿蔔1條",
      "水果醋適量",
      "鹽適量"
    ],
    "structured_ingredients": [
      {
        "name": "白蘿蔔",
        "quantity": 1.0,
        "unit": "條"
      },
      {
        "name": "水果醋",
        "quantity": "適量",
        "unit": null
      },
      {
        "name": "鹽",
        "quantity": "適量",
        "unit": null
      }
    ],
    "steps": [
      "•白蘿蔔→ 洗凈、削皮（刨刀削2次）、切丁（約 1cm 正方）, 蘿蔔丁約陶瓷碗1滿碗的量。\n\n• 想快速入味也可切片，差在口感不同。",
      "• 蘿蔔丁→ 裝入塑膠袋 or 保鮮盒，撒1",
      "2 茶匙鹽殺青，搖晃均勻，靜置約半小時，待其出水→ 倒入開水沖掉表面塩份。\n\n（若蘿蔔較多，請自行加塩量，但不要太多，太鹹就Orz，寧可少，也不要多，因即便不夠，後面醃的時間久些，入味後也很好吃的）",
      "• 將蘿蔔丁放入保鮮盒，倒入水果醋約5~7分滿即可，蓋上蓋子搖晃均勻，放隔夜再食用。\n\n• 先吃下層較入味，若一次吃的量大，則醋可倒多些。"
    ],
    "combined_text": "小菜_醃白蘿蔔（超簡單快速）。食材：白蘿蔔1條，水果醋適量，鹽適量。做法：•白蘿蔔→ 洗凈、削皮（刨刀削2次）、切丁（約 1cm 正方）, 蘿蔔丁約陶瓷碗1滿碗的量。\n\n• 想快速入味也可切片，差在口感不同。，• 蘿蔔丁→ 裝入塑膠袋 or 保鮮盒，撒1，2 茶匙鹽殺青，搖晃均勻，靜置約半小時，待其出水→ 倒入開水沖掉表面塩份。\n\n（若蘿蔔較多，請自行加塩量，但不要太多，太鹹就Orz，寧可少，也不要多，因即便不夠，後面醃的時間久些，入味後也很好吃的），• 將蘿蔔丁放入保鮮盒，倒入水果醋約5~7分滿即可，蓋上蓋子搖晃均勻，放隔夜再食用。\n\n• 先吃下層較入味，若一次吃的量大，則醋可倒多些。。",
    "image_path": "白蘿蔔/471183_小菜_醃白蘿蔔（超簡單快速）.jpg"
  },
  {
    "id": "465207",
    "name": "白蘿蔔燒肉",
    "url": "https://icook.tw/recipes/465207",
    "preview_ingredients": "五花肉、白蘿蔔、蔥、薑、蒜、辣椒、醬油、豆瓣醬、米酒、冰糖、熱水",
    "ingredients": [
      "五花肉300克",
      "白蘿蔔500克",
      "蔥20克",
      "薑20克",
      "蒜20克",
      "辣椒20克",
      "醬油3大匙",
      "豆瓣醬1大匙",
      "米酒2大匙",
      "冰糖1大匙",
      "熱水適量"
    ],
    "structured_ingredients": [
      {
        "name": "五花肉",
        "quantity": 300.0,
        "unit": "克"
      },
      {
        "name": "白蘿蔔",
        "quantity": 500.0,
        "unit": "克"
      },
      {
        "name": "蔥",
        "quantity": 20.0,
        "unit": "克"
      },
      {
        "name": "薑",
        "quantity": 20.0,
        "unit": "克"
      },
      {
        "name": "蒜",
        "quantity": 20.0,
        "unit": "克"
      },
      {
        "name": "辣椒",
        "quantity": 20.0,
        "unit": "克"
      },
      {
        "name": "醬油",
        "quantity": 3.0,
        "unit": "大匙"
      },
      {
        "name": "豆瓣醬",
        "quantity": 1.0,
        "unit": "大匙"
      },
      {
        "name": "米酒",
        "quantity": 2.0,
        "unit": "大匙"
      },
      {
        "name": "冰糖",
        "quantity": 1.0,
        "unit": "大匙"
      },
      {
        "name": "熱水",
        "quantity": "適量",
        "unit": null
      }
    ],
    "steps": [
      "食材",
      "❶白蘿蔔切小塊，五花肉切條狀\n❷鍋子不放油，直接放入五花肉煸炒出豬油，，取出過多的油脂\n❸放入蔥薑蒜辣椒炒香，再放入調味料，醬油、豆瓣、米酒、冰糖，炒出醬香\n❹加熱水約6-7分滿，燜煮20分鐘，再放入白蘿蔔，繼續燜煮20分鐘，開蓋大火收汁即可"
    ],
    "combined_text": "白蘿蔔燒肉。食材：五花肉300克，白蘿蔔500克，蔥20克，薑20克，蒜20克，辣椒20克，醬油3大匙，豆瓣醬1大匙，米酒2大匙，冰糖1大匙，熱水適量。做法：食材，❶白蘿蔔切小塊，五花肉切條狀\n❷鍋子不放油，直接放入五花肉煸炒出豬油，，取出過多的油脂\n❸放入蔥薑蒜辣椒炒香，再放入調味料，醬油、豆瓣、米酒、冰糖，炒出醬香\n❹加熱水約6-7分滿，燜煮20分鐘，再放入白蘿蔔，繼續燜煮20分鐘，開蓋大火收汁即可。",
    "image_path": "白蘿蔔/465207_白蘿蔔燒肉.jpg"
  },
  {
    "id": "451333",
    "name": "白蘿蔔香菇肉絲粥（電子鍋）",
    "url": "https://icook.tw/recipes/451333",
    "preview_ingredients": "白蘿蔔、肉絲、米酒、乾香菇、鹽、鹽巴、油蔥酥、香油、雞粉、米、胡椒粉",
    "ingredients": [
      "白蘿蔔0.5條",
      "肉絲200克",
      "乾香菇30克",
      "油蔥酥3大匙",
      "米1.5米杯",
      "米酒1大匙",
      "鹽1小匙",
      "香油1小匙",
      "鹽巴2小匙",
      "雞粉3大匙",
      "胡椒粉少許"
    ],
    "structured_ingredients": [
      {
        "name": "白蘿蔔",
        "quantity": 0.5,
        "unit": "條"
      },
      {
        "name": "肉絲",
        "quantity": 200.0,
        "unit": "克"
      },
      {
        "name": "乾香菇",
        "quantity": 30.0,
        "unit": "克"
      },
      {
        "name": "油蔥酥",
        "quantity": 3.0,
        "unit": "大匙"
      },
      {
        "name": "米",
        "quantity": 1.5,
        "unit": "米杯"
      },
      {
        "name": "米酒",
        "quantity": 1.0,
        "unit": "大匙"
      },
      {
        "name": "鹽",
        "quantity": 1.0,
        "unit": "小匙"
      },
      {
        "name": "香油",
        "quantity": 1.0,
        "unit": "小匙"
      },
      {
        "name": "鹽巴",
        "quantity": 2.0,
        "unit": "小匙"
      },
      {
        "name": "雞粉",
        "quantity": 3.0,
        "unit": "大匙"
      },
      {
        "name": "胡椒粉",
        "quantity": "少許",
        "unit": null
      }
    ],
    "steps": [
      "將蘿蔔刨成絲，肉絲使用米酒鹽巴香油醃漬10分鐘，香菇泡水軟化後切成絲",
      "熱油鍋爆香香菇絲加入豬肉絲甘草再放入白蘿蔔絲",
      "米洗淨後將炒料加入雞粉和胡椒粉炒拌均勻加水和米一同倒入電子鍋煮",
      "起鍋後可加油蔥酥及芹菜提味"
    ],
    "combined_text": "白蘿蔔香菇肉絲粥（電子鍋）。食材：白蘿蔔0.5條，肉絲200克，乾香菇30克，油蔥酥3大匙，米1.5米杯，米酒1大匙，鹽1小匙，香油1小匙，鹽巴2小匙，雞粉3大匙，胡椒粉少許。做法：將蘿蔔刨成絲，肉絲使用米酒鹽巴香油醃漬10分鐘，香菇泡水軟化後切成絲，熱油鍋爆香香菇絲加入豬肉絲甘草再放入白蘿蔔絲，米洗淨後將炒料加入雞粉和胡椒粉炒拌均勻加水和米一同倒入電子鍋煮，起鍋後可加油蔥酥及芹菜提味。",
    "image_path": "白蘿蔔/451333_白蘿蔔香菇肉絲粥（電子鍋）.jpg"
  },
  {
    "id": "479562",
    "name": "紅燒蘿蔔 / 家常菜",
    "url": "https://icook.tw/recipes/479562",
    "preview_ingredients": "白蘿蔔、老薑片、蒜瓣、蠔油、水、油",
    "ingredients": [
      "白蘿蔔1條",
      "老薑片4片",
      "蒜瓣5顆",
      "蠔油3/4大匙",
      "水200cc",
      "油1.5小匙"
    ],
    "structured_ingredients": [
      {
        "name": "白蘿蔔",
        "quantity": 1.0,
        "unit": "條"
      },
      {
        "name": "老薑片",
        "quantity": 4.0,
        "unit": "片"
      },
      {
        "name": "蒜瓣",
        "quantity": 5.0,
        "unit": "顆"
      },
      {
        "name": "蠔油",
        "quantity": 0.75,
        "unit": "大匙"
      },
      {
        "name": "水",
        "quantity": 200.0,
        "unit": "cc"
      },
      {
        "name": "油",
        "quantity": 1.5,
        "unit": "小匙"
      }
    ],
    "steps": [
      "●日本進口的白蘿蔔3條100元，跟台灣的價格一樣，刷洗乾淨刨去外皮，切2公分左右方塊，切愈大塊燉煮時間需拉長。",
      "●老薑刷洗乾淨切片；蒜瓣洗過切掉蒂頭拍碎剝膜。\n●辣椒洗淨去籽剪斜片當盤飾用竟也忘了擺上(可省略)。\n●蔥洗淨用蔥白蔥綠交接剪細絲當盤飾用(可省略)。",
      "●鍋中小火加1.5小匙油，放薑片跟蒜瓣爆香。",
      "●聞到薑蒜香氣後把白蘿蔔塊倒進鍋中拌炒，再把蠔油跟水加進來，如果敢吃微辣可以撒1",
      "5小匙白胡椒粉(不在材料裡)，用炒匙翻拌讓每塊白蘿蔔塊都沾到紅燒醬汁。",
      "●小火，設定計時器20分鐘蓋鍋燉煮白蘿蔔，20分鐘到打開鍋蓋白蘿蔔已變透明代表已熟。",
      "●打開鍋蓋再煨煮5分鐘，讓紅燒醬汁收汁這樣白蘿蔔能更入味，熄火完成。",
      "簡單的最好吃。",
      "妳也太扯了白蘿蔔也可以近50篇食譜https:",
      "tinyurl.com",
      "mwvbh9wc"
    ],
    "combined_text": "紅燒蘿蔔 / 家常菜。食材：白蘿蔔1條，老薑片4片，蒜瓣5顆，蠔油3/4大匙，水200cc，油1.5小匙。做法：●日本進口的白蘿蔔3條100元，跟台灣的價格一樣，刷洗乾淨刨去外皮，切2公分左右方塊，切愈大塊燉煮時間需拉長。，●老薑刷洗乾淨切片；蒜瓣洗過切掉蒂頭拍碎剝膜。\n●辣椒洗淨去籽剪斜片當盤飾用竟也忘了擺上(可省略)。\n●蔥洗淨用蔥白蔥綠交接剪細絲當盤飾用(可省略)。，●鍋中小火加1.5小匙油，放薑片跟蒜瓣爆香。，●聞到薑蒜香氣後把白蘿蔔塊倒進鍋中拌炒，再把蠔油跟水加進來，如果敢吃微辣可以撒1，5小匙白胡椒粉(不在材料裡)，用炒匙翻拌讓每塊白蘿蔔塊都沾到紅燒醬汁。，●小火，設定計時器20分鐘蓋鍋燉煮白蘿蔔，20分鐘到打開鍋蓋白蘿蔔已變透明代表已熟。，●打開鍋蓋再煨煮5分鐘，讓紅燒醬汁收汁這樣白蘿蔔能更入味，熄火完成。，簡單的最好吃。，妳也太扯了白蘿蔔也可以近50篇食譜https:，tinyurl.com，mwvbh9wc。",
    "image_path": "白蘿蔔/479562_紅燒蘿蔔___家常菜.jpg"
  },
  {
    "id": "479722",
    "name": "玉米蘿蔔湯",
    "url": "https://icook.tw/recipes/479722",
    "preview_ingredients": "白蘿蔔、紅蘿蔔、玉米、香菜、香油、胡椒粉、鹽、雞粉",
    "ingredients": [
      "白蘿蔔半條",
      "紅蘿蔔幾片",
      "玉米1條",
      "香菜少許",
      "香油少許",
      "胡椒粉少許",
      "鹽少許",
      "雞粉少許"
    ],
    "structured_ingredients": [
      {
        "name": "白蘿蔔",
        "quantity": 0.5,
        "unit": "條"
      },
      {
        "name": "紅蘿蔔幾片",
        "quantity": null,
        "unit": null
      },
      {
        "name": "玉米",
        "quantity": 1.0,
        "unit": "條"
      },
      {
        "name": "香菜",
        "quantity": "少許",
        "unit": null
      },
      {
        "name": "香油",
        "quantity": "少許",
        "unit": null
      },
      {
        "name": "胡椒粉",
        "quantity": "少許",
        "unit": null
      },
      {
        "name": "鹽",
        "quantity": "少許",
        "unit": null
      },
      {
        "name": "雞粉",
        "quantity": "少許",
        "unit": null
      }
    ],
    "steps": [
      "白蘿蔔切片入鍋 冷水就下鍋一起煮到滾 \n轉中小火繼續煮 蓋鍋蓋",
      "中間加入玉米、紅蘿蔔煮一下\n加入調味料試味道",
      "煮約45-60分鐘白蘿蔔煮透起鍋"
    ],
    "combined_text": "玉米蘿蔔湯。食材：白蘿蔔半條，紅蘿蔔幾片，玉米1條，香菜少許，香油少許，胡椒粉少許，鹽少許，雞粉少許。做法：白蘿蔔切片入鍋 冷水就下鍋一起煮到滾 \n轉中小火繼續煮 蓋鍋蓋，中間加入玉米、紅蘿蔔煮一下\n加入調味料試味道，煮約45-60分鐘白蘿蔔煮透起鍋。",
    "image_path": "白蘿蔔/479722_玉米蘿蔔湯.jpg"
  },
  {
    "id": "479515",
    "name": "炒蘿蔔絲",
    "url": "https://icook.tw/recipes/479515",
    "preview_ingredients": "白蘿蔔、糖、鹽、香菇素蠔油、水",
    "ingredients": [
      "白蘿蔔半條",
      "糖1小匙",
      "鹽1小匙",
      "香菇素蠔油1大匙",
      "水1量米杯"
    ],
    "structured_ingredients": [
      {
        "name": "白蘿蔔",
        "quantity": 0.5,
        "unit": "條"
      },
      {
        "name": "糖",
        "quantity": 1.0,
        "unit": "小匙"
      },
      {
        "name": "鹽",
        "quantity": 1.0,
        "unit": "小匙"
      },
      {
        "name": "香菇素蠔油",
        "quantity": 1.0,
        "unit": "大匙"
      },
      {
        "name": "水",
        "quantity": 1.0,
        "unit": "量米杯"
      }
    ],
    "steps": [
      "白蘿蔔刨絲",
      "下鍋放油白蘿蔔放入鍋中 拌炒\n加鹽",
      "糖\n1個量米杯的水\n拌炒至蘿蔔 軟嫩",
      "淋上香菇素蠔油\n即完成"
    ],
    "combined_text": "炒蘿蔔絲。食材：白蘿蔔半條，糖1小匙，鹽1小匙，香菇素蠔油1大匙，水1量米杯。做法：白蘿蔔刨絲，下鍋放油白蘿蔔放入鍋中 拌炒\n加鹽，糖\n1個量米杯的水\n拌炒至蘿蔔 軟嫩，淋上香菇素蠔油\n即完成。",
    "image_path": "白蘿蔔/479515_炒蘿蔔絲.jpg"
  },
  {
    "id": "477176",
    "name": "蘿蔔糕",
    "url": "https://icook.tw/recipes/477176",
    "preview_ingredients": "白蘿蔔泥、香腸丁、鹽、乾蝦米、味醂、乾香菇、白胡椒、泡完香菇的水、油蔥酥、水磨在來米粉、水",
    "ingredients": [
      "白蘿蔔泥500克",
      "香腸丁100克",
      "乾蝦米10克",
      "乾香菇5朵",
      "泡完香菇的水120克",
      "油蔥酥1大匙",
      "水磨在來米粉150克",
      "水250克",
      "鹽1小匙",
      "味醂1小匙",
      "白胡椒1小匙"
    ],
    "structured_ingredients": [
      {
        "name": "白蘿蔔泥",
        "quantity": 500.0,
        "unit": "克"
      },
      {
        "name": "香腸丁",
        "quantity": 100.0,
        "unit": "克"
      },
      {
        "name": "乾蝦米",
        "quantity": 10.0,
        "unit": "克"
      },
      {
        "name": "乾香菇",
        "quantity": 5.0,
        "unit": "朵"
      },
      {
        "name": "泡完香菇的水",
        "quantity": 120.0,
        "unit": "克"
      },
      {
        "name": "油蔥酥",
        "quantity": 1.0,
        "unit": "大匙"
      },
      {
        "name": "水磨在來米粉",
        "quantity": 150.0,
        "unit": "克"
      },
      {
        "name": "水",
        "quantity": 250.0,
        "unit": "克"
      },
      {
        "name": "鹽",
        "quantity": 1.0,
        "unit": "小匙"
      },
      {
        "name": "味醂",
        "quantity": 1.0,
        "unit": "小匙"
      },
      {
        "name": "白胡椒",
        "quantity": 1.0,
        "unit": "小匙"
      }
    ],
    "steps": [
      "乾香菇稍微洗過後，我是直接用加冷水，放進微波爐3分半，待涼捏乾切丁，泡香菇的水要留著，乾蝦米稍微洗過瀝乾，香腸我是用一般的香腸來取代臘腸，先蒸熟，待涼切成小丁。",
      "白蘿蔔去皮切塊，不用加水，不用加水，不用加水，很重要，說三遍，直接打成泥就可以了。",
      "不沾鍋，冷鍋，不用油，小火，下香菇丁、蝦米，炒至乾香。",
      "一樣保持小火，下香腸丁，我沒加油，因為我覺得香腸很油了，大約炒3分鐘。",
      "下白蘿蔔泥，中小火，繼續炒。",
      "炒大約10分鐘，蘿蔔水收乾，關火。鍋子不用洗。",
      "加入剛剛泡乾香菇的水，我加了120cc的香菇水，若是不夠，用自來水補足即可，放入調味料，再移到電鍋裏蒸，外鍋放一杯水，跳起來後，悶十分鐘，出鍋。",
      "將在來米粉和水攪拌均勻，倒入蒸好的料裡，放油蔥酥，再倒入剛剛的炒鍋裡，小火，要一直攪拌直到糊化，關火。",
      "先將容器刷上油，再倒入料，用湯匙或刮刀抹平表面，電鍋外鍋三杯水，蒸好跳起，悶10分鐘，取出，表面刷油，可防止乾裂，一定要帶涼透了才能取出切塊，或是冰冰箱冷藏一晚，隔天再切，煎至金黃，完成。"
    ],
    "combined_text": "蘿蔔糕。食材：白蘿蔔泥500克，香腸丁100克，乾蝦米10克，乾香菇5朵，泡完香菇的水120克，油蔥酥1大匙，水磨在來米粉150克，水250克，鹽1小匙，味醂1小匙，白胡椒1小匙。做法：乾香菇稍微洗過後，我是直接用加冷水，放進微波爐3分半，待涼捏乾切丁，泡香菇的水要留著，乾蝦米稍微洗過瀝乾，香腸我是用一般的香腸來取代臘腸，先蒸熟，待涼切成小丁。，白蘿蔔去皮切塊，不用加水，不用加水，不用加水，很重要，說三遍，直接打成泥就可以了。，不沾鍋，冷鍋，不用油，小火，下香菇丁、蝦米，炒至乾香。，一樣保持小火，下香腸丁，我沒加油，因為我覺得香腸很油了，大約炒3分鐘。，下白蘿蔔泥，中小火，繼續炒。，炒大約10分鐘，蘿蔔水收乾，關火。鍋子不用洗。，加入剛剛泡乾香菇的水，我加了120cc的香菇水，若是不夠，用自來水補足即可，放入調味料，再移到電鍋裏蒸，外鍋放一杯水，跳起來後，悶十分鐘，出鍋。，將在來米粉和水攪拌均勻，倒入蒸好的料裡，放油蔥酥，再倒入剛剛的炒鍋裡，小火，要一直攪拌直到糊化，關火。，先將容器刷上油，再倒入料，用湯匙或刮刀抹平表面，電鍋外鍋三杯水，蒸好跳起，悶10分鐘，取出，表面刷油，可防止乾裂，一定要帶涼透了才能取出切塊，或是冰冰箱冷藏一晚，隔天再切，煎至金黃，完成。。",
    "image_path": "白蘿蔔/477176_蘿蔔糕.jpg"
  },
  {
    "id": "479245",
    "name": "炸蘿蔔糕",
    "url": "https://icook.tw/recipes/479245",
    "preview_ingredients": "蘿蔔糕、麵粉、油",
    "ingredients": [
      "蘿蔔糕100克",
      "麵粉30克",
      "油100毫升"
    ],
    "structured_ingredients": [
      {
        "name": "蘿蔔糕",
        "quantity": 100.0,
        "unit": "克"
      },
      {
        "name": "麵粉",
        "quantity": 30.0,
        "unit": "克"
      },
      {
        "name": "油",
        "quantity": 100.0,
        "unit": "毫升"
      }
    ],
    "steps": [
      "1.蘿蔔糕切塊",
      "酥炸粉加水和",
      "油鍋準備好\n2.蘿蔔糕沾麵衣",
      "下油鍋炸\n3.起鍋前火開大一點再起鍋"
    ],
    "combined_text": "炸蘿蔔糕。食材：蘿蔔糕100克，麵粉30克，油100毫升。做法：1.蘿蔔糕切塊，酥炸粉加水和，油鍋準備好\n2.蘿蔔糕沾麵衣，下油鍋炸\n3.起鍋前火開大一點再起鍋。",
    "image_path": "白蘿蔔/479245_炸蘿蔔糕.jpg"
  },
  {
    "id": "462230",
    "name": "醬油醃白蘿蔔",
    "url": "https://icook.tw/recipes/462230",
    "preview_ingredients": "水、醬油、蒜頭辣椒、蘿蔔、糖、鹽、玻璃罐",
    "ingredients": [
      "水1碗",
      "醬油1碗",
      "蒜頭辣椒適量",
      "蘿蔔1~2條",
      "糖1大匙 可放可不放",
      "鹽適量",
      "玻璃罐3個"
    ],
    "structured_ingredients": [
      {
        "name": "水",
        "quantity": 1.0,
        "unit": "碗"
      },
      {
        "name": "醬油",
        "quantity": 1.0,
        "unit": "碗"
      },
      {
        "name": "蒜頭辣椒",
        "quantity": "適量",
        "unit": null
      },
      {
        "name": "蘿蔔",
        "quantity": "1~2",
        "unit": "條"
      },
      {
        "name": "糖",
        "quantity": 1.0,
        "unit": "大匙 可放可不放"
      },
      {
        "name": "鹽",
        "quantity": "適量",
        "unit": null
      },
      {
        "name": "玻璃罐",
        "quantity": 3.0,
        "unit": "個"
      }
    ],
    "steps": [
      "先把蘿蔔切片 然後用鹽殺青\n然後用保鮮膜包起來冰到冰箱\n（科普一下殺青的意思食材中加入鹽巴搓揉、拌勻，破壞蔬菜表皮細胞、使蔬菜本身的酵素失去活性，有助於去除苦澀味，並讓調味料更容易滲透進去；待食材出水後，再用清水沖洗乾淨並瀝乾，便能用來烹飪、涼拌，或是延長鹽巴醃漬時間做成漬物）",
      "一碗水一碗醬油 一大匙的糖\n放到鍋子裡面煮到滾起來就可以關火",
      "等到醬油冷卻以後 在拿出玻璃罐 放入蘿蔔蒜頭辣椒跟醬油就可以了\n（這裡建議隔天再裝 這樣殺青會殺的比較完整\n另外殺青的水不要倒到罐子裡面 也要把蘿蔔擠乾一點在放到罐子裡面喔）"
    ],
    "combined_text": "醬油醃白蘿蔔。食材：水1碗，醬油1碗，蒜頭辣椒適量，蘿蔔1~2條，糖1大匙 可放可不放，鹽適量，玻璃罐3個。做法：先把蘿蔔切片 然後用鹽殺青\n然後用保鮮膜包起來冰到冰箱\n（科普一下殺青的意思食材中加入鹽巴搓揉、拌勻，破壞蔬菜表皮細胞、使蔬菜本身的酵素失去活性，有助於去除苦澀味，並讓調味料更容易滲透進去；待食材出水後，再用清水沖洗乾淨並瀝乾，便能用來烹飪、涼拌，或是延長鹽巴醃漬時間做成漬物），一碗水一碗醬油 一大匙的糖\n放到鍋子裡面煮到滾起來就可以關火，等到醬油冷卻以後 在拿出玻璃罐 放入蘿蔔蒜頭辣椒跟醬油就可以了\n（這裡建議隔天再裝 這樣殺青會殺的比較完整\n另外殺青的水不要倒到罐子裡面 也要把蘿蔔擠乾一點在放到罐子裡面喔）。",
    "image_path": "白蘿蔔/462230_醬油醃白蘿蔔.jpg"
  },
  {
    "id": "461590",
    "name": "醬滷白蘿蔔",
    "url": "https://icook.tw/recipes/461590",
    "preview_ingredients": "白蘿蔔、薑、蒜頭、素蠔油、白胡椒粉",
    "ingredients": [
      "白蘿蔔1條",
      "薑1小塊",
      "蒜頭2小瓣",
      "素蠔油適量",
      "白胡椒粉些許"
    ],
    "structured_ingredients": [
      {
        "name": "白蘿蔔",
        "quantity": 1.0,
        "unit": "條"
      },
      {
        "name": "薑",
        "quantity": 1.0,
        "unit": "小塊"
      },
      {
        "name": "蒜頭",
        "quantity": 2.0,
        "unit": "小瓣"
      },
      {
        "name": "素蠔油",
        "quantity": "適量",
        "unit": null
      },
      {
        "name": "白胡椒粉",
        "quantity": "些許",
        "unit": null
      }
    ],
    "steps": [
      "將白蘿蔔切掉皮後，切成片狀，厚度約為小拇指寬，放進鍋中，再將薑切2小片，蒜拍扁後，一銅放入鍋中",
      "加入適量素蠔油和些許白胡椒粉調味，再加入清水淹過白蘿蔔後，攪拌均勻，放入電鍋中，外鍋放兩杯水，電鍋跳起後，看看蘿蔔是否能輕易戳破，不行的話就再多燉煮一杯水，可以的話就完成了！"
    ],
    "combined_text": "醬滷白蘿蔔。食材：白蘿蔔1條，薑1小塊，蒜頭2小瓣，素蠔油適量，白胡椒粉些許。做法：將白蘿蔔切掉皮後，切成片狀，厚度約為小拇指寬，放進鍋中，再將薑切2小片，蒜拍扁後，一銅放入鍋中，加入適量素蠔油和些許白胡椒粉調味，再加入清水淹過白蘿蔔後，攪拌均勻，放入電鍋中，外鍋放兩杯水，電鍋跳起後，看看蘿蔔是否能輕易戳破，不行的話就再多燉煮一杯水，可以的話就完成了！。",
    "image_path": "白蘿蔔/461590_醬滷白蘿蔔.jpg"
  },
  {
    "id": "462897",
    "name": "白蘿蔔豬肉餡水餃",
    "url": "https://icook.tw/recipes/462897",
    "preview_ingredients": "小條白蘿蔔、絞肉、蔥花、醬油",
    "ingredients": [
      "小條白蘿蔔1條",
      "絞肉300g",
      "蔥花少許",
      "醬油1.5匙"
    ],
    "structured_ingredients": [
      {
        "name": "小條白蘿蔔",
        "quantity": 1.0,
        "unit": "條"
      },
      {
        "name": "絞肉",
        "quantity": 300.0,
        "unit": "g"
      },
      {
        "name": "蔥花",
        "quantity": "少許",
        "unit": null
      },
      {
        "name": "醬油",
        "quantity": 1.5,
        "unit": "匙"
      }
    ],
    "steps": [
      "白蘿蔔去皮刨絲，放置10分，擰去白蘿蔔的水分",
      "絞肉用醬油醃製一下，再與蔥花攪拌均勻",
      "然後將白蘿蔔絲倒入絞肉中與絞肉攪拌均勻，然後靜置10分鐘",
      "然後包入餃子皮內即可，要吃時再放入滾水裡煮"
    ],
    "combined_text": "白蘿蔔豬肉餡水餃。食材：小條白蘿蔔1條，絞肉300g，蔥花少許，醬油1.5匙。做法：白蘿蔔去皮刨絲，放置10分，擰去白蘿蔔的水分，絞肉用醬油醃製一下，再與蔥花攪拌均勻，然後將白蘿蔔絲倒入絞肉中與絞肉攪拌均勻，然後靜置10分鐘，然後包入餃子皮內即可，要吃時再放入滾水裡煮。",
    "image_path": "白蘿蔔/462897_白蘿蔔豬肉餡水餃.jpg"
  },
  {
    "id": "470559",
    "name": "冬季限定～白蘿蔔牛腩湯（附蘸醬）",
    "url": "https://icook.tw/recipes/470559",
    "preview_ingredients": "牛腩、白蘿蔔、蒜末、薑片、辣椒、八角、香菜末、香菜、醬油、開水",
    "ingredients": [
      "牛腩600克",
      "白蘿蔔1條",
      "薑片5片",
      "八角1顆",
      "香菜適量",
      "蒜末2瓣",
      "辣椒0.5條",
      "香菜末少許",
      "醬油1小匙",
      "開水少許"
    ],
    "structured_ingredients": [
      {
        "name": "牛腩",
        "quantity": 600.0,
        "unit": "克"
      },
      {
        "name": "白蘿蔔",
        "quantity": 1.0,
        "unit": "條"
      },
      {
        "name": "薑片",
        "quantity": 5.0,
        "unit": "片"
      },
      {
        "name": "八角",
        "quantity": 1.0,
        "unit": "顆"
      },
      {
        "name": "香菜",
        "quantity": "適量",
        "unit": null
      },
      {
        "name": "蒜末",
        "quantity": 2.0,
        "unit": "瓣"
      },
      {
        "name": "辣椒",
        "quantity": 0.5,
        "unit": "條"
      },
      {
        "name": "香菜末",
        "quantity": "少許",
        "unit": null
      },
      {
        "name": "醬油",
        "quantity": 1.0,
        "unit": "小匙"
      },
      {
        "name": "開水",
        "quantity": "少許",
        "unit": null
      }
    ],
    "steps": [
      "1）牛腩切大塊",
      "冷水入鍋加薑片、米酒汆燙後撈出備用\n2）放入鑄鐵鍋",
      "加入水、薑片、八角",
      "大火煮滾後轉小火慢燉一小時\n3）續入白蘿蔔煮至蘿蔔熟透（變透明）\n4）加入鹽、白胡椒粉、香菜後即完成\n5）牛肉搭配蘸料",
      "很好吃喔！"
    ],
    "combined_text": "冬季限定～白蘿蔔牛腩湯（附蘸醬）。食材：牛腩600克，白蘿蔔1條，薑片5片，八角1顆，香菜適量，蒜末2瓣，辣椒0.5條，香菜末少許，醬油1小匙，開水少許。做法：1）牛腩切大塊，冷水入鍋加薑片、米酒汆燙後撈出備用\n2）放入鑄鐵鍋，加入水、薑片、八角，大火煮滾後轉小火慢燉一小時\n3）續入白蘿蔔煮至蘿蔔熟透（變透明）\n4）加入鹽、白胡椒粉、香菜後即完成\n5）牛肉搭配蘸料，很好吃喔！。",
    "image_path": "白蘿蔔/470559_冬季限定～白蘿蔔牛腩湯（附蘸醬）.jpg"
  },
  {
    "id": "461515",
    "name": "醃製紅蘿蔔白蘿蔔",
    "url": "https://icook.tw/recipes/461515",
    "preview_ingredients": "紅蘿蔔丁、白蘿蔔、鹽巴、蒜頭、辣椒",
    "ingredients": [
      "紅蘿蔔丁0.5根",
      "白蘿蔔0.5根",
      "鹽巴1小匙",
      "蒜頭3粒",
      "辣椒5片"
    ],
    "structured_ingredients": [
      {
        "name": "紅蘿蔔丁",
        "quantity": 0.5,
        "unit": "根"
      },
      {
        "name": "白蘿蔔",
        "quantity": 0.5,
        "unit": "根"
      },
      {
        "name": "鹽巴",
        "quantity": 1.0,
        "unit": "小匙"
      },
      {
        "name": "蒜頭",
        "quantity": 3.0,
        "unit": "粒"
      },
      {
        "name": "辣椒",
        "quantity": 5.0,
        "unit": "片"
      }
    ],
    "steps": [
      "這次我沒有先用鹽巴去腥紅蘿蔔白蘿蔔切丁後",
      "滾水川燙蒜頭切片加萬用醋\n鹽巴少許辣椒少許\n超好吃的日式醃菜完成"
    ],
    "combined_text": "醃製紅蘿蔔白蘿蔔。食材：紅蘿蔔丁0.5根，白蘿蔔0.5根，鹽巴1小匙，蒜頭3粒，辣椒5片。做法：這次我沒有先用鹽巴去腥紅蘿蔔白蘿蔔切丁後，滾水川燙蒜頭切片加萬用醋\n鹽巴少許辣椒少許\n超好吃的日式醃菜完成。",
    "image_path": "白蘿蔔/461515_醃製紅蘿蔔白蘿蔔.jpg"
  },
  {
    "id": "479556",
    "name": "蒜苗炒蘿蔔糕",
    "url": "https://icook.tw/recipes/479556",
    "preview_ingredients": "蘿蔔糕、香菜、蒜苗",
    "ingredients": [
      "蘿蔔糕300克",
      "香菜1把",
      "蒜苗1把"
    ],
    "structured_ingredients": [
      {
        "name": "蘿蔔糕",
        "quantity": 300.0,
        "unit": "克"
      },
      {
        "name": "香菜",
        "quantity": 1.0,
        "unit": "把"
      },
      {
        "name": "蒜苗",
        "quantity": 1.0,
        "unit": "把"
      }
    ],
    "steps": [
      "起鍋下油，煎蘿蔔糕",
      "煎至兩面金黃酥脆",
      "原鍋下蒜白炒香",
      "蘿蔔糕及蒜綠一同下鍋",
      "加入香菜拌炒的，即可調味起鍋"
    ],
    "combined_text": "蒜苗炒蘿蔔糕。食材：蘿蔔糕300克，香菜1把，蒜苗1把。做法：起鍋下油，煎蘿蔔糕，煎至兩面金黃酥脆，原鍋下蒜白炒香，蘿蔔糕及蒜綠一同下鍋，加入香菜拌炒的，即可調味起鍋。",
    "image_path": "白蘿蔔/479556_蒜苗炒蘿蔔糕.jpg"
  },
  {
    "id": "473910",
    "name": "蘿蔔蒸肉",
    "url": "https://icook.tw/recipes/473910",
    "preview_ingredients": "白蘿蔔、鹽、豬絞肉、蔥花，切碎、薑末、蠔油、食用油",
    "ingredients": [
      "白蘿蔔半條(約500G",
      "鹽1/2小匙",
      "豬絞肉約400G",
      "蔥花，切碎2大匙",
      "薑末1大匙",
      "蠔油2大匙",
      "食用油3大匙"
    ],
    "structured_ingredients": [
      {
        "name": "白蘿蔔半條(約",
        "quantity": 500.0,
        "unit": "G"
      },
      {
        "name": "鹽",
        "quantity": 0.5,
        "unit": "小匙"
      },
      {
        "name": "豬絞肉約",
        "quantity": 400.0,
        "unit": "G"
      },
      {
        "name": "蔥花，切碎",
        "quantity": 2.0,
        "unit": "大匙"
      },
      {
        "name": "薑末",
        "quantity": 1.0,
        "unit": "大匙"
      },
      {
        "name": "蠔油",
        "quantity": 2.0,
        "unit": "大匙"
      },
      {
        "name": "食用油",
        "quantity": 3.0,
        "unit": "大匙"
      }
    ],
    "steps": [
      "白蘿蔔去皮後橫切薄片(或用刨刀)，加鹽抓拌殺青，再用清水沖洗瀝乾。",
      "肉餡調味後加食用油，拌至有黏性，依蘿蔔片數量等分成小團。",
      "蘿蔔片中間放肉餡，將蘿蔔片二側與肉餡捏合呈夾餅狀。",
      "將步驟3成品擺入深盤，放進大同電鍋以1杯水蒸熟即可食用。"
    ],
    "combined_text": "蘿蔔蒸肉。食材：白蘿蔔半條(約500G，鹽1/2小匙，豬絞肉約400G，蔥花，切碎2大匙，薑末1大匙，蠔油2大匙，食用油3大匙。做法：白蘿蔔去皮後橫切薄片(或用刨刀)，加鹽抓拌殺青，再用清水沖洗瀝乾。，肉餡調味後加食用油，拌至有黏性，依蘿蔔片數量等分成小團。，蘿蔔片中間放肉餡，將蘿蔔片二側與肉餡捏合呈夾餅狀。，將步驟3成品擺入深盤，放進大同電鍋以1杯水蒸熟即可食用。。",
    "image_path": "白蘿蔔/473910_蘿蔔蒸肉.jpg"
  },
  {
    "id": "463014",
    "name": "日式白蘿蔔牛肉湯",
    "url": "https://icook.tw/recipes/463014",
    "preview_ingredients": "牛腱心、洋蔥、白蘿蔔、柴魚醬油",
    "ingredients": [
      "牛腱心1公斤",
      "洋蔥1顆",
      "白蘿蔔1條",
      "柴魚醬油適量"
    ],
    "structured_ingredients": [
      {
        "name": "牛腱心",
        "quantity": 1.0,
        "unit": "公斤"
      },
      {
        "name": "洋蔥",
        "quantity": 1.0,
        "unit": "顆"
      },
      {
        "name": "白蘿蔔",
        "quantity": 1.0,
        "unit": "條"
      },
      {
        "name": "柴魚醬油",
        "quantity": "適量",
        "unit": null
      }
    ],
    "steps": [
      "牛肉切小塊，洋蔥切絲，白蘿蔔去皮切小塊備用",
      "牛肉放進鍋中，加入清水淹過牛肉，加熱煮到牛肉表面變白色，即可撈出，將燙過的牛肉和切好的白蘿蔔放入空鍋中",
      "炒鍋內放入些許油，炒香洋蔥，洋蔥炒到半透明後，倒入牛肉和白蘿蔔鍋中，加入適量的柴魚醬油和清水，水要淹過所有材料，放入電鍋中，外鍋總共需要八杯水（可分兩次加），電鍋跳起後，就完成了"
    ],
    "combined_text": "日式白蘿蔔牛肉湯。食材：牛腱心1公斤，洋蔥1顆，白蘿蔔1條，柴魚醬油適量。做法：牛肉切小塊，洋蔥切絲，白蘿蔔去皮切小塊備用，牛肉放進鍋中，加入清水淹過牛肉，加熱煮到牛肉表面變白色，即可撈出，將燙過的牛肉和切好的白蘿蔔放入空鍋中，炒鍋內放入些許油，炒香洋蔥，洋蔥炒到半透明後，倒入牛肉和白蘿蔔鍋中，加入適量的柴魚醬油和清水，水要淹過所有材料，放入電鍋中，外鍋總共需要八杯水（可分兩次加），電鍋跳起後，就完成了。",
    "image_path": "白蘿蔔/463014_日式白蘿蔔牛肉湯.jpg"
  },
  {
    "id": "478688",
    "name": "蘿蔔玉米排骨湯",
    "url": "https://icook.tw/recipes/478688",
    "preview_ingredients": "玉米、白蘿蔔、鹽、豬小排、味精、雞湯塊、水",
    "ingredients": [
      "玉米1根",
      "白蘿蔔半根",
      "豬小排250克",
      "鹽適量",
      "味精適量",
      "雞湯塊1塊",
      "水750毫升"
    ],
    "structured_ingredients": [
      {
        "name": "玉米",
        "quantity": 1.0,
        "unit": "根"
      },
      {
        "name": "白蘿蔔",
        "quantity": 0.5,
        "unit": "根"
      },
      {
        "name": "豬小排",
        "quantity": 250.0,
        "unit": "克"
      },
      {
        "name": "鹽",
        "quantity": "適量",
        "unit": null
      },
      {
        "name": "味精",
        "quantity": "適量",
        "unit": null
      },
      {
        "name": "雞湯塊",
        "quantity": 1.0,
        "unit": "塊"
      },
      {
        "name": "水",
        "quantity": 750.0,
        "unit": "毫升"
      }
    ],
    "steps": [
      "白蘿蔔洗乾淨去皮切小塊、玉米洗乾淨切小塊。",
      "排骨用水川燙一下。",
      "準備另一鍋水，加入川燙好的排骨、白蘿蔔，加入調味料，燉煮到白蘿蔔熟透。",
      "白蘿蔔變成透明狀，再加入玉米煮一下，如果想要玉米甜味到湯頭，一開始就可以加，想保留玉米甜味好吃，就等到白蘿蔔熟了，再加入煮一下。"
    ],
    "combined_text": "蘿蔔玉米排骨湯。食材：玉米1根，白蘿蔔半根，豬小排250克，鹽適量，味精適量，雞湯塊1塊，水750毫升。做法：白蘿蔔洗乾淨去皮切小塊、玉米洗乾淨切小塊。，排骨用水川燙一下。，準備另一鍋水，加入川燙好的排骨、白蘿蔔，加入調味料，燉煮到白蘿蔔熟透。，白蘿蔔變成透明狀，再加入玉米煮一下，如果想要玉米甜味到湯頭，一開始就可以加，想保留玉米甜味好吃，就等到白蘿蔔熟了，再加入煮一下。。",
    "image_path": "白蘿蔔/478688_蘿蔔玉米排骨湯.jpg"
  },
  {
    "id": "478954",
    "name": "彩色蕃茄蘿蔔沙拉",
    "url": "https://icook.tw/recipes/478954",
    "preview_ingredients": "各色彩色蕃茄、彩色蘿蔔、香菜(可不用)、蒜頭(可不用)、紅酒醋(視個人口味調整)、初榨橄欖油(視個人口味調整)、鹽(視個人口味調整)、黑胡椒粉(可不用)",
    "ingredients": [
      "各色彩色蕃茄20顆",
      "彩色蘿蔔2條",
      "香菜(可不用)1株",
      "蒜頭(可不用)1瓣",
      "紅酒醋(視個人口味調整)1大匙",
      "初榨橄欖油(視個人口味調整)2大匙",
      "鹽(視個人口味調整)1小匙",
      "黑胡椒粉(可不用)約半小匙"
    ],
    "structured_ingredients": [
      {
        "name": "各色彩色蕃茄",
        "quantity": 20.0,
        "unit": "顆"
      },
      {
        "name": "彩色蘿蔔",
        "quantity": 2.0,
        "unit": "條"
      },
      {
        "name": "香菜(可不用)",
        "quantity": 1.0,
        "unit": "株"
      },
      {
        "name": "蒜頭(可不用)",
        "quantity": 1.0,
        "unit": "瓣"
      },
      {
        "name": "紅酒醋(視個人口味調整)",
        "quantity": 1.0,
        "unit": "大匙"
      },
      {
        "name": "初榨橄欖油(視個人口味調整)",
        "quantity": 2.0,
        "unit": "大匙"
      },
      {
        "name": "鹽(視個人口味調整)",
        "quantity": 1.0,
        "unit": "小匙"
      },
      {
        "name": "黑胡椒粉",
        "quantity": null,
        "unit": null
      }
    ],
    "steps": [
      "彩色蘿蔔洗淨，帶皮用削皮刀削成薄片",
      "蘿蔔片加1小匙鹽（份量外）抓一抓，靜置約10分鐘殺青",
      "彩色蕃茄對半切、香菜切小段、蒜頭切碎，備用",
      "紅酒醋、橄欖油、鹽、黑胡椒粉拌勻，試一下味道，調整到自己喜歡的味道後備用",
      "蘿蔔片用飲用水把鹽份洗淨，瀝乾，與蕃茄放入一個大碗中，少量多次加油醋醬拌勻，加到自己喜歡的鹹淡即可",
      "最後上面灑上香菜即可上桌",
      "外加一個簡單的烤彩色蘿蔔：彩色蘿蔔洗淨，直條一開四。灑點鹽及胡椒，淋上一些橄欖油，烤箱預熱180度烤約15分鐘即可。",
      "因為可生吃，所以也可以單純烤熱，或是想拿出來就拿出來。"
    ],
    "combined_text": "彩色蕃茄蘿蔔沙拉。食材：各色彩色蕃茄20顆，彩色蘿蔔2條，香菜(可不用)1株，蒜頭(可不用)1瓣，紅酒醋(視個人口味調整)1大匙，初榨橄欖油(視個人口味調整)2大匙，鹽(視個人口味調整)1小匙，黑胡椒粉(可不用)約半小匙。做法：彩色蘿蔔洗淨，帶皮用削皮刀削成薄片，蘿蔔片加1小匙鹽（份量外）抓一抓，靜置約10分鐘殺青，彩色蕃茄對半切、香菜切小段、蒜頭切碎，備用，紅酒醋、橄欖油、鹽、黑胡椒粉拌勻，試一下味道，調整到自己喜歡的味道後備用，蘿蔔片用飲用水把鹽份洗淨，瀝乾，與蕃茄放入一個大碗中，少量多次加油醋醬拌勻，加到自己喜歡的鹹淡即可，最後上面灑上香菜即可上桌，外加一個簡單的烤彩色蘿蔔：彩色蘿蔔洗淨，直條一開四。灑點鹽及胡椒，淋上一些橄欖油，烤箱預熱180度烤約15分鐘即可。，因為可生吃，所以也可以單純烤熱，或是想拿出來就拿出來。。",
    "image_path": "白蘿蔔/478954_彩色蕃茄蘿蔔沙拉.jpg"
  },
  {
    "id": "477329",
    "name": "味噌炒紅蘿蔔豬肉",
    "url": "https://icook.tw/recipes/477329",
    "preview_ingredients": "豬瘦絞肉、米酒、鹽、胡椒、味噌、糖、紅蘿蔔、大蒜、毛豆、海苔",
    "ingredients": [
      "豬瘦絞肉1盒",
      "米酒1大匙",
      "鹽0.5小匙",
      "胡椒0.5大匙",
      "味噌1大匙",
      "糖1小匙",
      "紅蘿蔔1條",
      "大蒜1瓣",
      "毛豆3大匙",
      "海苔1片"
    ],
    "structured_ingredients": [
      {
        "name": "豬瘦絞肉",
        "quantity": 1.0,
        "unit": "盒"
      },
      {
        "name": "米酒",
        "quantity": 1.0,
        "unit": "大匙"
      },
      {
        "name": "鹽",
        "quantity": 0.5,
        "unit": "小匙"
      },
      {
        "name": "胡椒",
        "quantity": 0.5,
        "unit": "大匙"
      },
      {
        "name": "味噌",
        "quantity": 1.0,
        "unit": "大匙"
      },
      {
        "name": "糖",
        "quantity": 1.0,
        "unit": "小匙"
      },
      {
        "name": "紅蘿蔔",
        "quantity": 1.0,
        "unit": "條"
      },
      {
        "name": "大蒜",
        "quantity": 1.0,
        "unit": "瓣"
      },
      {
        "name": "毛豆",
        "quantity": 3.0,
        "unit": "大匙"
      },
      {
        "name": "海苔",
        "quantity": 1.0,
        "unit": "片"
      }
    ],
    "steps": [
      "材料如圖。",
      "絞肉混合鹽、胡椒和米酒，抓醃入味。",
      "取小碗混合味增、糖和少許熱水。",
      "像這樣。",
      "紅蘿蔔刨絲、大蒜切片。",
      "熱鍋加少許油，加入絞肉，炒至表面變色。",
      "先這樣就可以先乘起備用。",
      "鍋子裡再補一點油，放入大蒜爆香。",
      "加入紅蘿蔔絲拌炒。",
      "待紅蘿蔔變軟加入味噌水。",
      "再把剛剛炒上色的絞肉倒回去。",
      "加入毛豆，再半炒個3分鐘或直到絞肉熟透。",
      "盛盤後加上剪成絲的海苔裝飾一下。"
    ],
    "combined_text": "味噌炒紅蘿蔔豬肉。食材：豬瘦絞肉1盒，米酒1大匙，鹽0.5小匙，胡椒0.5大匙，味噌1大匙，糖1小匙，紅蘿蔔1條，大蒜1瓣，毛豆3大匙，海苔1片。做法：材料如圖。，絞肉混合鹽、胡椒和米酒，抓醃入味。，取小碗混合味增、糖和少許熱水。，像這樣。，紅蘿蔔刨絲、大蒜切片。，熱鍋加少許油，加入絞肉，炒至表面變色。，先這樣就可以先乘起備用。，鍋子裡再補一點油，放入大蒜爆香。，加入紅蘿蔔絲拌炒。，待紅蘿蔔變軟加入味噌水。，再把剛剛炒上色的絞肉倒回去。，加入毛豆，再半炒個3分鐘或直到絞肉熟透。，盛盤後加上剪成絲的海苔裝飾一下。。",
    "image_path": "白蘿蔔/477329_味噌炒紅蘿蔔豬肉.jpg"
  },
  {
    "id": "457197",
    "name": "無水白蘿蔔燉肉",
    "url": "https://icook.tw/recipes/457197",
    "preview_ingredients": "豬梅花肉切塊、白蘿蔔、八角、月桂葉、鹽巴、黑胡椒粉、醬油、糖、紹興酒",
    "ingredients": [
      "豬梅花肉切塊450公克",
      "白蘿蔔1條",
      "八角1個",
      "月桂葉1片",
      "鹽巴1/4大湯匙",
      "黑胡椒粉1/4大湯匙",
      "醬油3大湯匙",
      "糖1大湯匙",
      "紹興酒2大湯匙"
    ],
    "structured_ingredients": [
      {
        "name": "豬梅花肉切塊",
        "quantity": 450.0,
        "unit": "公克"
      },
      {
        "name": "白蘿蔔",
        "quantity": 1.0,
        "unit": "條"
      },
      {
        "name": "八角",
        "quantity": 1.0,
        "unit": "個"
      },
      {
        "name": "月桂葉",
        "quantity": 1.0,
        "unit": "片"
      },
      {
        "name": "鹽巴",
        "quantity": 0.25,
        "unit": "大湯匙"
      },
      {
        "name": "黑胡椒粉",
        "quantity": 0.25,
        "unit": "大湯匙"
      },
      {
        "name": "醬油",
        "quantity": 3.0,
        "unit": "大湯匙"
      },
      {
        "name": "糖",
        "quantity": 1.0,
        "unit": "大湯匙"
      },
      {
        "name": "紹興酒",
        "quantity": 2.0,
        "unit": "大湯匙"
      }
    ],
    "steps": [
      "將豬肉與醃料混合醃製半小時",
      "將白蘿蔔削2層皮後切塊備用",
      "冷鍋加入1大湯匙的油，開中大火等到油熱加入梅花肉煎至表面金黃",
      "加入白蘿蔔拌炒30秒",
      "加入所有調味料拌炒一下並加入八角及月桂葉",
      "蓋上鍋蓋開小火燉煮45分鐘即可收工(每15分鐘攪拌一次)"
    ],
    "combined_text": "無水白蘿蔔燉肉。食材：豬梅花肉切塊450公克，白蘿蔔1條，八角1個，月桂葉1片，鹽巴1/4大湯匙，黑胡椒粉1/4大湯匙，醬油3大湯匙，糖1大湯匙，紹興酒2大湯匙。做法：將豬肉與醃料混合醃製半小時，將白蘿蔔削2層皮後切塊備用，冷鍋加入1大湯匙的油，開中大火等到油熱加入梅花肉煎至表面金黃，加入白蘿蔔拌炒30秒，加入所有調味料拌炒一下並加入八角及月桂葉，蓋上鍋蓋開小火燉煮45分鐘即可收工(每15分鐘攪拌一次)。",
    "image_path": "白蘿蔔/457197_無水白蘿蔔燉肉.jpg"
  },
  {
    "id": "473243",
    "name": "特福鮮呼吸電子壓力鍋-白蘿蔔雞腿藥膳湯",
    "url": "https://icook.tw/recipes/473243",
    "preview_ingredients": "藥膳藥材、水、鮮味炒手、米酒、海鹽、帶骨雞腿肉、白蘿蔔",
    "ingredients": [
      "藥膳藥材1包",
      "水3大碗",
      "米酒1米杯",
      "帶骨雞腿肉4支",
      "白蘿蔔1條",
      "鮮味炒手2匙",
      "海鹽少許"
    ],
    "structured_ingredients": [
      {
        "name": "藥膳藥材",
        "quantity": 1.0,
        "unit": "包"
      },
      {
        "name": "水",
        "quantity": 3.0,
        "unit": "大碗"
      },
      {
        "name": "米酒",
        "quantity": 1.0,
        "unit": "米杯"
      },
      {
        "name": "帶骨雞腿肉",
        "quantity": 4.0,
        "unit": "支"
      },
      {
        "name": "白蘿蔔",
        "quantity": 1.0,
        "unit": "條"
      },
      {
        "name": "鮮味炒手",
        "quantity": 2.0,
        "unit": "匙"
      },
      {
        "name": "海鹽",
        "quantity": "少許",
        "unit": null
      }
    ],
    "steps": [
      "將食材材料包都丟入特福鮮呼吸萬用鍋中",
      "用雞肉模式",
      "洩壓後就完成"
    ],
    "combined_text": "特福鮮呼吸電子壓力鍋-白蘿蔔雞腿藥膳湯。食材：藥膳藥材1包，水3大碗，米酒1米杯，帶骨雞腿肉4支，白蘿蔔1條，鮮味炒手2匙，海鹽少許。做法：將食材材料包都丟入特福鮮呼吸萬用鍋中，用雞肉模式，洩壓後就完成。",
    "image_path": "白蘿蔔/473243_特福鮮呼吸電子壓力鍋-白蘿蔔雞腿藥膳湯.jpg"
  },
  {
    "id": "455089",
    "name": "白蘿蔔牛肉湯",
    "url": "https://icook.tw/recipes/455089",
    "preview_ingredients": "牛肋條、牛腱、老薑、白蘿蔔、八角、米酒、蔥、醬油、冰糖、白胡椒粉、鹽、水",
    "ingredients": [
      "牛肋條500克",
      "牛腱600克",
      "白蘿蔔1條",
      "老薑20克",
      "八角6粒",
      "蔥1支",
      "米酒150cc",
      "醬油5大匙",
      "冰糖1大匙",
      "白胡椒粉適量",
      "鹽1小匙",
      "水1800cc"
    ],
    "structured_ingredients": [
      {
        "name": "牛肋條",
        "quantity": 500.0,
        "unit": "克"
      },
      {
        "name": "牛腱",
        "quantity": 600.0,
        "unit": "克"
      },
      {
        "name": "白蘿蔔",
        "quantity": 1.0,
        "unit": "條"
      },
      {
        "name": "老薑",
        "quantity": 20.0,
        "unit": "克"
      },
      {
        "name": "八角",
        "quantity": 6.0,
        "unit": "粒"
      },
      {
        "name": "蔥",
        "quantity": 1.0,
        "unit": "支"
      },
      {
        "name": "米酒",
        "quantity": 150.0,
        "unit": "cc"
      },
      {
        "name": "醬油",
        "quantity": 5.0,
        "unit": "大匙"
      },
      {
        "name": "冰糖",
        "quantity": 1.0,
        "unit": "大匙"
      },
      {
        "name": "白胡椒粉",
        "quantity": "適量",
        "unit": null
      },
      {
        "name": "鹽",
        "quantity": 1.0,
        "unit": "小匙"
      },
      {
        "name": "水",
        "quantity": 1800.0,
        "unit": "cc"
      }
    ],
    "steps": [
      "將牛肋條切塊",
      "煎到表面熟",
      "放入切好的牛腱炒",
      "加入米酒炒香",
      "用另一個鍋子加入1800cc的水和炒好的牛肉",
      "煮滾加入八角",
      "加入醬油",
      "加入冰糖",
      "適量白胡椒粉",
      "將雜質撈乾淨，加入白蘿蔔和蔥",
      "蓋上蓋子小火煮1小時（留小縫）",
      "將八角取出",
      "加鹽",
      "最後加ㄧ小匙的冰糖"
    ],
    "combined_text": "白蘿蔔牛肉湯。食材：牛肋條500克，牛腱600克，白蘿蔔1條，老薑20克，八角6粒，蔥1支，米酒150cc，醬油5大匙，冰糖1大匙，白胡椒粉適量，鹽1小匙，水1800cc。做法：將牛肋條切塊，煎到表面熟，放入切好的牛腱炒，加入米酒炒香，用另一個鍋子加入1800cc的水和炒好的牛肉，煮滾加入八角，加入醬油，加入冰糖，適量白胡椒粉，將雜質撈乾淨，加入白蘿蔔和蔥，蓋上蓋子小火煮1小時（留小縫），將八角取出，加鹽，最後加ㄧ小匙的冰糖。",
    "image_path": "白蘿蔔/455089_白蘿蔔牛肉湯.jpg"
  },
  {
    "id": "477452",
    "name": "青檸醃蘿蔔",
    "url": "https://icook.tw/recipes/477452",
    "preview_ingredients": "白蘿蔔、水、檸檬、替代檸檬（現成檸檬冰角）、白醋、冰糖、鹽",
    "ingredients": [
      "白蘿蔔1大條",
      "水750c.c",
      "檸檬2個",
      "替代檸檬（現成檸檬冰角）2包",
      "白醋2杯",
      "冰糖適量",
      "鹽少許"
    ],
    "structured_ingredients": [
      {
        "name": "白蘿蔔",
        "quantity": 1.0,
        "unit": "大條"
      },
      {
        "name": "水",
        "quantity": 750.0,
        "unit": "c.c"
      },
      {
        "name": "檸檬",
        "quantity": 2.0,
        "unit": "個"
      },
      {
        "name": "替代檸檬（現成檸檬冰角）",
        "quantity": 2.0,
        "unit": "包"
      },
      {
        "name": "白醋",
        "quantity": 2.0,
        "unit": "杯"
      },
      {
        "name": "冰糖",
        "quantity": "適量",
        "unit": null
      },
      {
        "name": "鹽",
        "quantity": "少許",
        "unit": null
      }
    ],
    "steps": [
      "將蘿蔔洗乾淨去皮，對半切後切片加入鹽巴抓醃放置15分鐘後，用開水沖洗後擠乾",
      "冰糖、醋、檸檬、水加入鍋中加熱，調出自己喜歡的甜酸度，待蘿蔔放入瓶中，加入醬汁冰封，隔日即可食用。"
    ],
    "combined_text": "青檸醃蘿蔔。食材：白蘿蔔1大條，水750c.c，檸檬2個，替代檸檬（現成檸檬冰角）2包，白醋2杯，冰糖適量，鹽少許。做法：將蘿蔔洗乾淨去皮，對半切後切片加入鹽巴抓醃放置15分鐘後，用開水沖洗後擠乾，冰糖、醋、檸檬、水加入鍋中加熱，調出自己喜歡的甜酸度，待蘿蔔放入瓶中，加入醬汁冰封，隔日即可食用。。",
    "image_path": "白蘿蔔/477452_青檸醃蘿蔔.jpg"
  },
  {
    "id": "472314",
    "name": "台式蘿蔔糕",
    "url": "https://icook.tw/recipes/472314",
    "preview_ingredients": "白蘿蔔絲、水、在來米(舊米最好)、鹽巴16克、白胡椒粉2克",
    "ingredients": [
      "白蘿蔔絲1800克",
      "水720克",
      "鹽巴16克4小匙",
      "白胡椒粉2克1.5小匙",
      "在來米(舊米最好)600",
      "水600"
    ],
    "structured_ingredients": [
      {
        "name": "白蘿蔔絲",
        "quantity": 1800.0,
        "unit": "克"
      },
      {
        "name": "水",
        "quantity": 720.0,
        "unit": "克"
      },
      {
        "name": "鹽巴16克",
        "quantity": 4.0,
        "unit": "小匙"
      },
      {
        "name": "白胡椒粉2克",
        "quantity": 1.5,
        "unit": "小匙"
      },
      {
        "name": "在來米(舊米最好)",
        "quantity": 60.0,
        "unit": "0"
      },
      {
        "name": "水",
        "quantity": 60.0,
        "unit": "0"
      }
    ],
    "steps": [
      "食材：白蘿蔔2條約4斤，使用3斤蘿蔔絲(多的可以煮蘿蔔排骨湯)\n在來米1斤\n鹽巴4小匙\n白胡椒粉1.5小匙",
      "模具：\n蘿蔔糕模1個(十人份大同電鍋適用），模具有小圓孔裡面鋪烘焙紙\n磅蛋糕模2個(30公分蒸籠適用），模具內層抹一層薄薄的油幫助好脫模\n蘿蔔糕模購買連結：https:",
      "s.shopee.tw",
      "4fi6KpsKwh磅蛋糕膜購買連結：https:",
      "s.shopee.tw",
      "3AtIY4y2zQ",
      "1斤米泡水後瀝乾水分的米秤重約758克（米600+水158克）\n\nPS:在來米洗淨後倒入約2倍水，泡水放冰箱冷藏4 -6小時",
      "將泡水後的米再加入清水到米水的重量加起來共1200克（米600+水600）\n\nPS：米：水=1：1",
      "在來米漿做法：米水倒入容杯預留半米杯的水，用研磨功能鍵打成米漿",
      "米漿倒到容器中，用預留的半杯水洗出殘留的米漿",
      "白蘿蔔削皮，用切片器刨絲\n\nAROMA不鏽鋼切片器切量多的食材可以加快速度並輕鬆完成\n購買連結：https:",
      "s.shopee.tw",
      "AUftJLZxnY",
      "鍋內倒入些許油熱鍋",
      "倒入刨好的蘿蔔絲到鍋內用中火煮，過程中翻拌避免焦底",
      "用中火慢煮就會出水~~",
      "煮到蘿蔔出水去掉蘿蔔的生味後，倒入清水後煮滾",
      "另一口爐預煮一鍋滾水\n\nPS：寬30公分深13公分湯鍋，至少加到一半的高度",
      "蘿蔔絲加入鹽巴、白胡椒粉，翻拌均勻，蓋鍋蓋悶煮5分鐘煮軟變透明狀",
      "倒入打好的米漿\n\nPS：米漿打好會沉澱，使用前用刮刀拌開",
      "開小火煮蘿蔔米糊",
      "兩手各拿一支刮刀或是鍋鏟翻拌，中途如果快焦底可以先關火翻拌，過一會兒再開火繼續拌",
      "加熱攪拌到水狀米糊的透明感變成白色稠狀米糊",
      "分裝到模具內，模具邊緣跟外緣擦乾淨",
      "方形模具放入電鍋內蓋上蓋子，電鍋外鍋3米杯水(約蒸30分鐘)。電鍋跳起來後，等個20分鐘，再加2米杯水，再蒸約20分鐘，按鍵跳起來，即可。",
      "另2個長型模具放入蒸籠蓋上蓋子，水煮滾大火蒸10分鐘，中大火蒸70分鐘，取出放涼脫模",
      "蒸好的蘿蔔糕完全冷卻後脫模",
      "冷卻後脫膜很容易",
      "冷卻後脫膜很容易",
      "長形蘿蔔糕對切放入酷藝師名作7號保鮮盒冷藏保存，賞味期7天。\n保鮮盒購買連結：https:",
      "s.shopee.tw",
      "1B8EDT3m6s",
      "方形蘿蔔糕對切，用2個酷藝師花神方形6號保鮮盒冷藏保存，賞味期7天。\n保鮮盒購買連結：https:",
      "s.shopee.tw",
      "AA3EB0yUaL",
      "蘿蔔糕要煎到恰恰才好吃，用鐵鍋煎蘿蔔糕，鍋子開火加熱倒入些許油脂，加熱到冒煙關火，等待約30秒讓鍋子充分熱鍋，這時再開中火放入蘿蔔糕就不會沾鍋非常好煎，煎到有焦香顏色出現翻面再煎，兩面都金黃漂亮即可起鍋。",
      "些許醬油、香油、烏醋，香菜切碎或是蒜泥沾著蘿蔔糕一起吃，光想都留口水。"
    ],
    "combined_text": "台式蘿蔔糕。食材：白蘿蔔絲1800克，水720克，鹽巴16克4小匙，白胡椒粉2克1.5小匙，在來米(舊米最好)600，水600。做法：食材：白蘿蔔2條約4斤，使用3斤蘿蔔絲(多的可以煮蘿蔔排骨湯)\n在來米1斤\n鹽巴4小匙\n白胡椒粉1.5小匙，模具：\n蘿蔔糕模1個(十人份大同電鍋適用），模具有小圓孔裡面鋪烘焙紙\n磅蛋糕模2個(30公分蒸籠適用），模具內層抹一層薄薄的油幫助好脫模\n蘿蔔糕模購買連結：https:，s.shopee.tw，4fi6KpsKwh磅蛋糕膜購買連結：https:，s.shopee.tw，3AtIY4y2zQ，1斤米泡水後瀝乾水分的米秤重約758克（米600+水158克）\n\nPS:在來米洗淨後倒入約2倍水，泡水放冰箱冷藏4 -6小時，將泡水後的米再加入清水到米水的重量加起來共1200克（米600+水600）\n\nPS：米：水=1：1，在來米漿做法：米水倒入容杯預留半米杯的水，用研磨功能鍵打成米漿，米漿倒到容器中，用預留的半杯水洗出殘留的米漿，白蘿蔔削皮，用切片器刨絲\n\nAROMA不鏽鋼切片器切量多的食材可以加快速度並輕鬆完成\n購買連結：https:，s.shopee.tw，AUftJLZxnY，鍋內倒入些許油熱鍋，倒入刨好的蘿蔔絲到鍋內用中火煮，過程中翻拌避免焦底，用中火慢煮就會出水~~，煮到蘿蔔出水去掉蘿蔔的生味後，倒入清水後煮滾，另一口爐預煮一鍋滾水\n\nPS：寬30公分深13公分湯鍋，至少加到一半的高度，蘿蔔絲加入鹽巴、白胡椒粉，翻拌均勻，蓋鍋蓋悶煮5分鐘煮軟變透明狀，倒入打好的米漿\n\nPS：米漿打好會沉澱，使用前用刮刀拌開，開小火煮蘿蔔米糊，兩手各拿一支刮刀或是鍋鏟翻拌，中途如果快焦底可以先關火翻拌，過一會兒再開火繼續拌，加熱攪拌到水狀米糊的透明感變成白色稠狀米糊，分裝到模具內，模具邊緣跟外緣擦乾淨，方形模具放入電鍋內蓋上蓋子，電鍋外鍋3米杯水(約蒸30分鐘)。電鍋跳起來後，等個20分鐘，再加2米杯水，再蒸約20分鐘，按鍵跳起來，即可。，另2個長型模具放入蒸籠蓋上蓋子，水煮滾大火蒸10分鐘，中大火蒸70分鐘，取出放涼脫模，蒸好的蘿蔔糕完全冷卻後脫模，冷卻後脫膜很容易，冷卻後脫膜很容易，長形蘿蔔糕對切放入酷藝師名作7號保鮮盒冷藏保存，賞味期7天。\n保鮮盒購買連結：https:，s.shopee.tw，1B8EDT3m6s，方形蘿蔔糕對切，用2個酷藝師花神方形6號保鮮盒冷藏保存，賞味期7天。\n保鮮盒購買連結：https:，s.shopee.tw，AA3EB0yUaL，蘿蔔糕要煎到恰恰才好吃，用鐵鍋煎蘿蔔糕，鍋子開火加熱倒入些許油脂，加熱到冒煙關火，等待約30秒讓鍋子充分熱鍋，這時再開中火放入蘿蔔糕就不會沾鍋非常好煎，煎到有焦香顏色出現翻面再煎，兩面都金黃漂亮即可起鍋。，些許醬油、香油、烏醋，香菜切碎或是蒜泥沾著蘿蔔糕一起吃，光想都留口水。。",
    "image_path": "白蘿蔔/472314_台式蘿蔔糕.jpg"
  },
  {
    "id": "473933",
    "name": "台式蘿蔔泡菜/素",
    "url": "https://icook.tw/recipes/473933",
    "preview_ingredients": "白蘿蔔、紅蘿蔔、蒜、白糖、糯米醋、辣椒、冰梅",
    "ingredients": [
      "白蘿蔔1條",
      "紅蘿蔔1條",
      "蒜8瓣",
      "白糖100克",
      "糯米醋100克",
      "辣椒1條",
      "冰梅20克"
    ],
    "structured_ingredients": [
      {
        "name": "白蘿蔔",
        "quantity": 1.0,
        "unit": "條"
      },
      {
        "name": "紅蘿蔔",
        "quantity": 1.0,
        "unit": "條"
      },
      {
        "name": "蒜",
        "quantity": 8.0,
        "unit": "瓣"
      },
      {
        "name": "白糖",
        "quantity": 100.0,
        "unit": "克"
      },
      {
        "name": "糯米醋",
        "quantity": 100.0,
        "unit": "克"
      },
      {
        "name": "辣椒",
        "quantity": 1.0,
        "unit": "條"
      },
      {
        "name": "冰梅",
        "quantity": 20.0,
        "unit": "克"
      }
    ],
    "steps": [
      "先將所有材料備妥。",
      "紅、白蘿蔔先淨削皮並切成小塊，裝在碗中，分別加入1匙、1.5匙的鹽並用手拌一拌。",
      "將已煮過的冷水放入鍋中，開小火加熱到白糖可以融即熄火，再加入冰梅。放涼。",
      "將出水的白",
      "紅蘿蔔放入1500CC的白開水沖掉鹽份，再放入瀝水器內瀝乾。",
      "拿出一個乾淨的密封保鮮盒，將瀝乾的白",
      "紅蘿蔔放入，再放入醬汁，蓋上蓋子放入冰箱，隔天即完成。"
    ],
    "combined_text": "台式蘿蔔泡菜/素。食材：白蘿蔔1條，紅蘿蔔1條，蒜8瓣，白糖100克，糯米醋100克，辣椒1條，冰梅20克。做法：先將所有材料備妥。，紅、白蘿蔔先淨削皮並切成小塊，裝在碗中，分別加入1匙、1.5匙的鹽並用手拌一拌。，將已煮過的冷水放入鍋中，開小火加熱到白糖可以融即熄火，再加入冰梅。放涼。，將出水的白，紅蘿蔔放入1500CC的白開水沖掉鹽份，再放入瀝水器內瀝乾。，拿出一個乾淨的密封保鮮盒，將瀝乾的白，紅蘿蔔放入，再放入醬汁，蓋上蓋子放入冰箱，隔天即完成。。",
    "image_path": "白蘿蔔/473933_台式蘿蔔泡菜_素.jpg"
  },
  {
    "id": "476714",
    "name": "蘿蔔貢丸排骨湯",
    "url": "https://icook.tw/recipes/476714",
    "preview_ingredients": "胛心排骨、白蘿蔔、貢丸、老薑、香菜/芹菜、米酒、白胡椒粒、鹽、雞粉、冷水",
    "ingredients": [
      "胛心排骨一斤/800g",
      "白蘿蔔一大條/800g",
      "貢丸8顆",
      "老薑6片",
      "香菜/芹菜適量",
      "米酒4大匙",
      "白胡椒粒1大匙",
      "鹽1茶匙",
      "雞粉1茶匙",
      "冷水3公升"
    ],
    "structured_ingredients": [
      {
        "name": "胛心排骨一斤/",
        "quantity": 800.0,
        "unit": "g"
      },
      {
        "name": "白蘿蔔一大條/",
        "quantity": 800.0,
        "unit": "g"
      },
      {
        "name": "貢丸",
        "quantity": 8.0,
        "unit": "顆"
      },
      {
        "name": "老薑",
        "quantity": 6.0,
        "unit": "片"
      },
      {
        "name": "香菜/芹菜",
        "quantity": "適量",
        "unit": null
      },
      {
        "name": "米酒",
        "quantity": 4.0,
        "unit": "大匙"
      },
      {
        "name": "白胡椒粒",
        "quantity": 1.0,
        "unit": "大匙"
      },
      {
        "name": "鹽",
        "quantity": 1.0,
        "unit": "茶匙"
      },
      {
        "name": "雞粉",
        "quantity": 1.0,
        "unit": "茶匙"
      },
      {
        "name": "冷水",
        "quantity": 3.0,
        "unit": "公升"
      }
    ],
    "steps": [
      "白胡椒粒用石臼碾碎（或刀子拍破），裝入滷包中",
      "排骨焯水、洗淨，然後加入薑片、胡椒、米酒、清水燒開，中火燉煮45分鐘",
      "加入白蘿蔔、貢丸，繼續燉煮30~45分鐘",
      "熄火，調入鹽、雞粉",
      "清甜爽口的蘿蔔排骨湯完成",
      "也可以加入香菜末或芹菜珠"
    ],
    "combined_text": "蘿蔔貢丸排骨湯。食材：胛心排骨一斤/800g，白蘿蔔一大條/800g，貢丸8顆，老薑6片，香菜/芹菜適量，米酒4大匙，白胡椒粒1大匙，鹽1茶匙，雞粉1茶匙，冷水3公升。做法：白胡椒粒用石臼碾碎（或刀子拍破），裝入滷包中，排骨焯水、洗淨，然後加入薑片、胡椒、米酒、清水燒開，中火燉煮45分鐘，加入白蘿蔔、貢丸，繼續燉煮30~45分鐘，熄火，調入鹽、雞粉，清甜爽口的蘿蔔排骨湯完成，也可以加入香菜末或芹菜珠。",
    "image_path": "白蘿蔔/476714_蘿蔔貢丸排骨湯.jpg"
  },
  {
    "id": "478875",
    "name": "麻香蘿蔔絲餅",
    "url": "https://icook.tw/recipes/478875",
    "preview_ingredients": "白蘿蔔、胡蘿蔔、蔥花、蛋、麵粉、鹽巴、紅花椒鹽",
    "ingredients": [
      "白蘿蔔1根",
      "胡蘿蔔1/4根",
      "蔥花適量",
      "蛋1顆",
      "麵粉20公克",
      "鹽巴1小匙",
      "紅花椒鹽兩大匙"
    ],
    "structured_ingredients": [
      {
        "name": "白蘿蔔",
        "quantity": 1.0,
        "unit": "根"
      },
      {
        "name": "胡蘿蔔",
        "quantity": 0.25,
        "unit": "根"
      },
      {
        "name": "蔥花",
        "quantity": "適量",
        "unit": null
      },
      {
        "name": "蛋",
        "quantity": 1.0,
        "unit": "顆"
      },
      {
        "name": "麵粉",
        "quantity": 20.0,
        "unit": "公克"
      },
      {
        "name": "鹽巴",
        "quantity": 1.0,
        "unit": "小匙"
      },
      {
        "name": "紅花椒鹽",
        "quantity": 2,
        "unit": "大匙"
      }
    ],
    "steps": [
      "白蘿蔔和胡蘿蔔刨絲",
      "稍微加鹽拌勻靜置5–10分鐘出水\n擠乾水分（保留一些水分讓餅不會太乾）",
      "加入雞蛋",
      "攪拌均勻",
      "加入麵粉攪拌\n直到形成稍有黏性的麵糰狀",
      "加入蔥花、紅花椒鹽攪拌",
      "鍋中加少許油\n將餡料分成小份\n壓成扁平圓餅狀",
      "中小火兩面煎至金黃酥脆即可",
      "起鍋後可再灑上紅花椒鹽\n多了麻香感、鹹香開胃"
    ],
    "combined_text": "麻香蘿蔔絲餅。食材：白蘿蔔1根，胡蘿蔔1/4根，蔥花適量，蛋1顆，麵粉20公克，鹽巴1小匙，紅花椒鹽兩大匙。做法：白蘿蔔和胡蘿蔔刨絲，稍微加鹽拌勻靜置5–10分鐘出水\n擠乾水分（保留一些水分讓餅不會太乾），加入雞蛋，攪拌均勻，加入麵粉攪拌\n直到形成稍有黏性的麵糰狀，加入蔥花、紅花椒鹽攪拌，鍋中加少許油\n將餡料分成小份\n壓成扁平圓餅狀，中小火兩面煎至金黃酥脆即可，起鍋後可再灑上紅花椒鹽\n多了麻香感、鹹香開胃。",
    "image_path": "白蘿蔔/478875_麻香蘿蔔絲餅.jpg"
  },
  {
    "id": "478852",
    "name": "日式豚肉佃煮蘿蔔",
    "url": "https://icook.tw/recipes/478852",
    "preview_ingredients": "豬肉片、白蘿蔔、醬油、紅蘿蔔、味琳、薑片、米酒、蔥白段、糖、蒜頭、洋蔥絲、蔥花",
    "ingredients": [
      "豬肉片8片",
      "白蘿蔔半根",
      "紅蘿蔔半根",
      "薑片2片",
      "蔥白段4段",
      "蒜頭4瓣",
      "洋蔥絲少許",
      "蔥花少許",
      "醬油2匙",
      "味琳1匙",
      "米酒2匙",
      "糖1小匙"
    ],
    "structured_ingredients": [
      {
        "name": "豬肉片",
        "quantity": 8.0,
        "unit": "片"
      },
      {
        "name": "白蘿蔔",
        "quantity": 0.5,
        "unit": "根"
      },
      {
        "name": "紅蘿蔔",
        "quantity": 0.5,
        "unit": "根"
      },
      {
        "name": "薑片",
        "quantity": 2.0,
        "unit": "片"
      },
      {
        "name": "蔥白段",
        "quantity": 4.0,
        "unit": "段"
      },
      {
        "name": "蒜頭",
        "quantity": 4.0,
        "unit": "瓣"
      },
      {
        "name": "洋蔥絲",
        "quantity": "少許",
        "unit": null
      },
      {
        "name": "蔥花",
        "quantity": "少許",
        "unit": null
      },
      {
        "name": "醬油",
        "quantity": 2.0,
        "unit": "匙"
      },
      {
        "name": "味琳",
        "quantity": 1.0,
        "unit": "匙"
      },
      {
        "name": "米酒",
        "quantity": 2.0,
        "unit": "匙"
      },
      {
        "name": "糖",
        "quantity": 1.0,
        "unit": "小匙"
      }
    ],
    "steps": [
      "豬肉片加少許醬油.米酒醃漬30～40分鐘",
      "講紅白蘿蔔切片，少許洋蔥切成條狀蔥白4段，兩片薑及四瓣蒜頭",
      "將豬肉片下鍋煸出油後，加入蒜頭炒香",
      "肉夾出備用",
      "將薑片.蔥白.洋蔥下鍋炒香",
      "加入紅白蘿蔔，水沒過食材",
      "醬汁\n醬油兩匙.味琳ㄧ匙.糖ㄧ小匙.米酒兩匙",
      "水滾後加入調配好的醬汁",
      "蓋鍋蓋慢火燉至蘿蔔煮軟",
      "收汁後撒入蔥花",
      "充滿日式家庭風味的豚肉佃煮蘿蔔就完成啦！"
    ],
    "combined_text": "日式豚肉佃煮蘿蔔。食材：豬肉片8片，白蘿蔔半根，紅蘿蔔半根，薑片2片，蔥白段4段，蒜頭4瓣，洋蔥絲少許，蔥花少許，醬油2匙，味琳1匙，米酒2匙，糖1小匙。做法：豬肉片加少許醬油.米酒醃漬30～40分鐘，講紅白蘿蔔切片，少許洋蔥切成條狀蔥白4段，兩片薑及四瓣蒜頭，將豬肉片下鍋煸出油後，加入蒜頭炒香，肉夾出備用，將薑片.蔥白.洋蔥下鍋炒香，加入紅白蘿蔔，水沒過食材，醬汁\n醬油兩匙.味琳ㄧ匙.糖ㄧ小匙.米酒兩匙，水滾後加入調配好的醬汁，蓋鍋蓋慢火燉至蘿蔔煮軟，收汁後撒入蔥花，充滿日式家庭風味的豚肉佃煮蘿蔔就完成啦！。",
    "image_path": "白蘿蔔/478852_日式豚肉佃煮蘿蔔.jpg"
  },
  {
    "id": "479398",
    "name": "菜脯炒蘿蔔糕",
    "url": "https://icook.tw/recipes/479398",
    "preview_ingredients": "蘿蔔糕、雞蛋、蒜頭、菜脯、黑甜醬油、魚露、白胡椒粉、食用油或奶油、辣椒醬（可省略）",
    "ingredients": [
      "蘿蔔糕300克",
      "雞蛋2顆",
      "蒜頭3瓣",
      "菜脯2大匙",
      "黑甜醬油2大匙",
      "魚露1小匙",
      "白胡椒粉1大匙",
      "食用油或奶油1大匙",
      "辣椒醬（可省略）1大匙"
    ],
    "structured_ingredients": [
      {
        "name": "蘿蔔糕",
        "quantity": 300.0,
        "unit": "克"
      },
      {
        "name": "雞蛋",
        "quantity": 2.0,
        "unit": "顆"
      },
      {
        "name": "蒜頭",
        "quantity": 3.0,
        "unit": "瓣"
      },
      {
        "name": "菜脯",
        "quantity": 2.0,
        "unit": "大匙"
      },
      {
        "name": "黑甜醬油",
        "quantity": 2.0,
        "unit": "大匙"
      },
      {
        "name": "魚露",
        "quantity": 1.0,
        "unit": "小匙"
      },
      {
        "name": "白胡椒粉",
        "quantity": 1.0,
        "unit": "大匙"
      },
      {
        "name": "食用油或奶油",
        "quantity": 1.0,
        "unit": "大匙"
      },
      {
        "name": "辣椒醬（可省略）",
        "quantity": 1.0,
        "unit": "大匙"
      }
    ],
    "steps": [
      "預煮蘿蔔糕（可選）\n　👉 微波或蒸熱 30秒～1分鐘，讓它炒的時候比較軟。",
      "煎蘿蔔糕\n　- 鍋中放 1～2 匙油，加熱後下蘿蔔糕煎到金黃微焦（每面約 1~2 分鐘），推至鍋邊備用。",
      "爆香配料\n　- 再加一點油，放入蒜末＋蘿蔔乾（如有）爆香。\n　👉 若使用蝦醬辣椒，可以這時候一併炒香！\n加入辣椒醬\n　- 加入 1 大匙辣椒醬（看你口味，怕太辣先加半匙），炒勻與香料混合。",
      "下蛋拌炒\n　- 倒入蛋液，靜置 5 秒讓底部微定型，再快速拌炒，讓蛋裹住蘿蔔糕。",
      "調味與上色\n　- 加入黑甜醬油拌炒至整體上色。\n　- 用少許魚露／醬油調整鹹味。\n　- 灑白胡椒提香。"
    ],
    "combined_text": "菜脯炒蘿蔔糕。食材：蘿蔔糕300克，雞蛋2顆，蒜頭3瓣，菜脯2大匙，黑甜醬油2大匙，魚露1小匙，白胡椒粉1大匙，食用油或奶油1大匙，辣椒醬（可省略）1大匙。做法：預煮蘿蔔糕（可選）\n　👉 微波或蒸熱 30秒～1分鐘，讓它炒的時候比較軟。，煎蘿蔔糕\n　- 鍋中放 1～2 匙油，加熱後下蘿蔔糕煎到金黃微焦（每面約 1~2 分鐘），推至鍋邊備用。，爆香配料\n　- 再加一點油，放入蒜末＋蘿蔔乾（如有）爆香。\n　👉 若使用蝦醬辣椒，可以這時候一併炒香！\n加入辣椒醬\n　- 加入 1 大匙辣椒醬（看你口味，怕太辣先加半匙），炒勻與香料混合。，下蛋拌炒\n　- 倒入蛋液，靜置 5 秒讓底部微定型，再快速拌炒，讓蛋裹住蘿蔔糕。，調味與上色\n　- 加入黑甜醬油拌炒至整體上色。\n　- 用少許魚露／醬油調整鹹味。\n　- 灑白胡椒提香。。",
    "image_path": "白蘿蔔/479398_菜脯炒蘿蔔糕.jpg"
  },
  {
    "id": "471220",
    "name": "蘿蔔魚丸湯",
    "url": "https://icook.tw/recipes/471220",
    "preview_ingredients": "三鮮丸/花枝魚丸、白蘿蔔、老薑、芹菜/香菜、米酒、香油、雞粉、鹽、白胡椒粉、冷水",
    "ingredients": [
      "三鮮丸/花枝魚丸10顆/600g",
      "白蘿蔔400g",
      "老薑40g",
      "芹菜/香菜80g",
      "米酒2大匙",
      "香油1茶匙",
      "雞粉1茶匙",
      "鹽½茶匙",
      "白胡椒粉½茶匙",
      "冷水1.5ℓ"
    ],
    "structured_ingredients": [
      {
        "name": "三鮮丸/花枝魚丸10顆/",
        "quantity": 600.0,
        "unit": "g"
      },
      {
        "name": "白蘿蔔",
        "quantity": 400.0,
        "unit": "g"
      },
      {
        "name": "老薑",
        "quantity": 40.0,
        "unit": "g"
      },
      {
        "name": "芹菜/香菜",
        "quantity": 80.0,
        "unit": "g"
      },
      {
        "name": "米酒",
        "quantity": 2.0,
        "unit": "大匙"
      },
      {
        "name": "香油",
        "quantity": 1.0,
        "unit": "茶匙"
      },
      {
        "name": "雞粉",
        "quantity": 1.0,
        "unit": "茶匙"
      },
      {
        "name": "鹽",
        "quantity": 0.5,
        "unit": "茶匙"
      },
      {
        "name": "白胡椒粉",
        "quantity": 0.5,
        "unit": "茶匙"
      },
      {
        "name": "冷水",
        "quantity": 1.5,
        "unit": "ℓ"
      }
    ],
    "steps": [
      "白蘿蔔去皮，切成略帶厚度的薄片",
      "內鍋中加入白蘿蔔、老薑(拍破)、魚丸(不用解凍)、米酒、鹽、冷水",
      "外鍋放1杯水，煮至開關跳起，繼續保溫10~20分鐘",
      "調入雞粉、白胡椒粉、香油，最後撒上芹菜珠"
    ],
    "combined_text": "蘿蔔魚丸湯。食材：三鮮丸/花枝魚丸10顆/600g，白蘿蔔400g，老薑40g，芹菜/香菜80g，米酒2大匙，香油1茶匙，雞粉1茶匙，鹽½茶匙，白胡椒粉½茶匙，冷水1.5ℓ。做法：白蘿蔔去皮，切成略帶厚度的薄片，內鍋中加入白蘿蔔、老薑(拍破)、魚丸(不用解凍)、米酒、鹽、冷水，外鍋放1杯水，煮至開關跳起，繼續保溫10~20分鐘，調入雞粉、白胡椒粉、香油，最後撒上芹菜珠。",
    "image_path": "白蘿蔔/471220_蘿蔔魚丸湯.jpg"
  },
  {
    "id": "476383",
    "name": "簡易蘿蔔絲餅",
    "url": "https://icook.tw/recipes/476383",
    "preview_ingredients": "白蘿蔔、紅蘿蔔、蝦皮、雞蛋、青蔥、香菜、中筋麵粉、白胡椒、鹽、油",
    "ingredients": [
      "白蘿蔔半根",
      "紅蘿蔔半根",
      "蝦皮1大匙",
      "雞蛋2顆",
      "青蔥2根",
      "香菜2根",
      "中筋麵粉0.8杯",
      "白胡椒1小匙",
      "鹽1小匙",
      "油1小匙"
    ],
    "structured_ingredients": [
      {
        "name": "白蘿蔔",
        "quantity": 0.5,
        "unit": "根"
      },
      {
        "name": "紅蘿蔔",
        "quantity": 0.5,
        "unit": "根"
      },
      {
        "name": "蝦皮",
        "quantity": 1.0,
        "unit": "大匙"
      },
      {
        "name": "雞蛋",
        "quantity": 2.0,
        "unit": "顆"
      },
      {
        "name": "青蔥",
        "quantity": 2.0,
        "unit": "根"
      },
      {
        "name": "香菜",
        "quantity": 2.0,
        "unit": "根"
      },
      {
        "name": "中筋麵粉",
        "quantity": 0.8,
        "unit": "杯"
      },
      {
        "name": "白胡椒",
        "quantity": 1.0,
        "unit": "小匙"
      },
      {
        "name": "鹽",
        "quantity": 1.0,
        "unit": "小匙"
      },
      {
        "name": "油",
        "quantity": 1.0,
        "unit": "小匙"
      }
    ],
    "steps": [
      "紅蘿蔔刨絲，我喜歡有顏色，所以加紅蘿蔔，也可以不加",
      "白蘿蔔刨絲，加鹽靜置5分鐘後，擰乾水份",
      "青蔥、香菜切好",
      "蝦皮洗淨，白蘿蔔、紅蘿蔔絲、青蔥、香菜、蛋、胡椒、鹽、油，所有材料拌勻",
      "加入量米杯8分的中筋麵粉+量米杯2分的清水",
      "攪拌均勻",
      "已經有加油拌勻了，下鍋煎時，鍋油可放可不放",
      "煎至兩面金黃就能出鍋啦"
    ],
    "combined_text": "簡易蘿蔔絲餅。食材：白蘿蔔半根，紅蘿蔔半根，蝦皮1大匙，雞蛋2顆，青蔥2根，香菜2根，中筋麵粉0.8杯，白胡椒1小匙，鹽1小匙，油1小匙。做法：紅蘿蔔刨絲，我喜歡有顏色，所以加紅蘿蔔，也可以不加，白蘿蔔刨絲，加鹽靜置5分鐘後，擰乾水份，青蔥、香菜切好，蝦皮洗淨，白蘿蔔、紅蘿蔔絲、青蔥、香菜、蛋、胡椒、鹽、油，所有材料拌勻，加入量米杯8分的中筋麵粉+量米杯2分的清水，攪拌均勻，已經有加油拌勻了，下鍋煎時，鍋油可放可不放，煎至兩面金黃就能出鍋啦。",
    "image_path": "白蘿蔔/476383_簡易蘿蔔絲餅.jpg"
  },
  {
    "id": "478219",
    "name": "醃漬蘿蔔（柚子風味）",
    "url": "https://icook.tw/recipes/478219",
    "preview_ingredients": "白蘿蔔、開水、柚子茶、香菇調味露、壺釀米醋",
    "ingredients": [
      "白蘿蔔半條",
      "開水適量",
      "柚子茶2大匙",
      "香菇調味露2大匙",
      "壺釀米醋1大匙"
    ],
    "structured_ingredients": [
      {
        "name": "白蘿蔔",
        "quantity": 0.5,
        "unit": "條"
      },
      {
        "name": "開水",
        "quantity": "適量",
        "unit": null
      },
      {
        "name": "柚子茶",
        "quantity": 2.0,
        "unit": "大匙"
      },
      {
        "name": "香菇調味露",
        "quantity": 2.0,
        "unit": "大匙"
      },
      {
        "name": "壺釀米醋",
        "quantity": 1.0,
        "unit": "大匙"
      }
    ],
    "steps": [
      "白蘿蔔切成薄片",
      "講香菇調味露、柚子茶、壺釀米醋、水一起調勻\n煮到小滾關火",
      "放一旁等稍涼一點",
      "倒入保鮮盒裡醃漬白蘿蔔片，放入冰箱隔天即可享用"
    ],
    "combined_text": "醃漬蘿蔔（柚子風味）。食材：白蘿蔔半條，開水適量，柚子茶2大匙，香菇調味露2大匙，壺釀米醋1大匙。做法：白蘿蔔切成薄片，講香菇調味露、柚子茶、壺釀米醋、水一起調勻\n煮到小滾關火，放一旁等稍涼一點，倒入保鮮盒裡醃漬白蘿蔔片，放入冰箱隔天即可享用。",
    "image_path": "白蘿蔔/478219_醃漬蘿蔔（柚子風味）.jpg"
  },
  {
    "id": "439699",
    "name": "白蘿蔔冬粉湯",
    "url": "https://icook.tw/recipes/439699",
    "preview_ingredients": "白蘿蔔、冬粉、白胡椒粉、芹菜末、油蔥",
    "ingredients": [
      "白蘿蔔半條",
      "冬粉3個",
      "白胡椒粉少許",
      "芹菜末少許",
      "油蔥少許"
    ],
    "structured_ingredients": [
      {
        "name": "白蘿蔔",
        "quantity": 0.5,
        "unit": "條"
      },
      {
        "name": "冬粉",
        "quantity": 3.0,
        "unit": "個"
      },
      {
        "name": "白胡椒粉",
        "quantity": "少許",
        "unit": null
      },
      {
        "name": "芹菜末",
        "quantity": "少許",
        "unit": null
      },
      {
        "name": "油蔥",
        "quantity": "少許",
        "unit": null
      }
    ],
    "steps": [
      "冬粉事先泡軟備用",
      "鍋裡放入高湯(我用的是煮白切肉時的高湯)，然後白蘿蔔去皮刨絲，並將蘿蔔絲放入鍋中與高湯一起煮",
      "鍋中湯滾時加入蝦皮下去煮",
      "然後加入冬粉下去煮，並加入適量的鹽調味",
      "最後撒上白胡椒粉、芹菜末、油蔥即可"
    ],
    "combined_text": "白蘿蔔冬粉湯。食材：白蘿蔔半條，冬粉3個，白胡椒粉少許，芹菜末少許，油蔥少許。做法：冬粉事先泡軟備用，鍋裡放入高湯(我用的是煮白切肉時的高湯)，然後白蘿蔔去皮刨絲，並將蘿蔔絲放入鍋中與高湯一起煮，鍋中湯滾時加入蝦皮下去煮，然後加入冬粉下去煮，並加入適量的鹽調味，最後撒上白胡椒粉、芹菜末、油蔥即可。",
    "image_path": "白蘿蔔/439699_白蘿蔔冬粉湯.jpg"
  },
  {
    "id": "476350",
    "name": "辣牛肉蘿蔔湯",
    "url": "https://icook.tw/recipes/476350",
    "preview_ingredients": "李錦記 頭道零添加原釀醬油、牛肉 （切片）、辣椒粉、白蘿蔔 （切片）、香油、蔥 （切段）、昆布高湯、豆芽、鹽、蒜泥",
    "ingredients": [
      "李錦記 頭道零添加原釀醬油2大匙",
      "牛肉 （切片）200g",
      "白蘿蔔 （切片）200g",
      "蔥 （切段）1根",
      "豆芽200g",
      "蒜泥0.5大匙",
      "辣椒粉1大匙",
      "香油2大匙",
      "昆布高湯1000毫升",
      "鹽1茶匙"
    ],
    "structured_ingredients": [
      {
        "name": "李錦記 頭道零添加原釀醬油",
        "quantity": 2.0,
        "unit": "大匙"
      },
      {
        "name": "牛肉 （切片）",
        "quantity": 200.0,
        "unit": "g"
      },
      {
        "name": "白蘿蔔 （切片）",
        "quantity": 200.0,
        "unit": "g"
      },
      {
        "name": "蔥 （切段）",
        "quantity": 1.0,
        "unit": "根"
      },
      {
        "name": "豆芽",
        "quantity": 200.0,
        "unit": "g"
      },
      {
        "name": "蒜泥",
        "quantity": 0.5,
        "unit": "大匙"
      },
      {
        "name": "辣椒粉",
        "quantity": 1.0,
        "unit": "大匙"
      },
      {
        "name": "香油",
        "quantity": 2.0,
        "unit": "大匙"
      },
      {
        "name": "昆布高湯",
        "quantity": 1000.0,
        "unit": "毫升"
      },
      {
        "name": "鹽",
        "quantity": 1.0,
        "unit": "茶匙"
      }
    ],
    "steps": [
      "食材大集合。",
      "湯鍋中倒入2大匙芝麻油（香油），加入1大匙辣椒粉小火炒2分鐘。",
      "放入牛肉片中大火拌炒2分鐘，續加入白蘿蔔片與醬油大火拌炒5分鐘。\n「李錦記 頭道零添加原釀醬油」讓鮮味雙倍提升，醬香醇厚，鮮中回甘，回歸醬油本味，深層煥出食材原味。」的風味特點。",
      "倒入昆布高湯大火煮至沸騰。",
      "蓋上鍋蓋中小火燉煮20分鐘後，放黃豆芽、蔥段、蒜泥、鹽，煮5分鐘即可。",
      "「李錦記 頭道零添加原釀醬油」日式釀造工藝，風味獨特，醬香醇厚，鮮中回甘，零添加、純釀造配方，讓所有料理都能ㄧ瓶搞定，兼顧美味與健康，是我廚房裡不可或缺的神助手。",
      "同場加映：\n2到小菜「涼拌菠菜」與「辣蘿蔔泡菜」也是用「李錦記 頭道零添加原釀醬油 」來調整料理風味，再加入蒜泥、麻油、白芝麻，蘿蔔泡菜則額外加入白醋、糖和辣椒粉拌勻即可享用。",
      "牛肉搭配豐富的蔬菜一起熬煮的湯頭風味香辣濃郁，在乍暖還寒的春日裡喝上一碗熱呼呼的辣牛肉蘿蔔湯，讓人忍不住大呼過癮，暖身也暖心，作法並不困難，不妨試試！"
    ],
    "combined_text": "辣牛肉蘿蔔湯。食材：李錦記 頭道零添加原釀醬油2大匙，牛肉 （切片）200g，白蘿蔔 （切片）200g，蔥 （切段）1根，豆芽200g，蒜泥0.5大匙，辣椒粉1大匙，香油2大匙，昆布高湯1000毫升，鹽1茶匙。做法：食材大集合。，湯鍋中倒入2大匙芝麻油（香油），加入1大匙辣椒粉小火炒2分鐘。，放入牛肉片中大火拌炒2分鐘，續加入白蘿蔔片與醬油大火拌炒5分鐘。\n「李錦記 頭道零添加原釀醬油」讓鮮味雙倍提升，醬香醇厚，鮮中回甘，回歸醬油本味，深層煥出食材原味。」的風味特點。，倒入昆布高湯大火煮至沸騰。，蓋上鍋蓋中小火燉煮20分鐘後，放黃豆芽、蔥段、蒜泥、鹽，煮5分鐘即可。，「李錦記 頭道零添加原釀醬油」日式釀造工藝，風味獨特，醬香醇厚，鮮中回甘，零添加、純釀造配方，讓所有料理都能ㄧ瓶搞定，兼顧美味與健康，是我廚房裡不可或缺的神助手。，同場加映：\n2到小菜「涼拌菠菜」與「辣蘿蔔泡菜」也是用「李錦記 頭道零添加原釀醬油 」來調整料理風味，再加入蒜泥、麻油、白芝麻，蘿蔔泡菜則額外加入白醋、糖和辣椒粉拌勻即可享用。，牛肉搭配豐富的蔬菜一起熬煮的湯頭風味香辣濃郁，在乍暖還寒的春日裡喝上一碗熱呼呼的辣牛肉蘿蔔湯，讓人忍不住大呼過癮，暖身也暖心，作法並不困難，不妨試試！。",
    "image_path": "白蘿蔔/476350_辣牛肉蘿蔔湯.jpg"
  }
]